Workbook

Sheet FS & Trend Analysis
A2: Financial Statements of Diageo Ltd. | I2: Trend Analysis
A4: Income Statement | I4: Income Statement
A5: Particulars (Amount in Crores of INR) | B5: 46112 | C5: 45747 | D5: 45382 | E5: 45016 | F5: 44651 | G5: 44286 | I5: Particulars | J5: 46112 | K5: 45747 | L5: 45382 | M5: 45016 | N5: 44651 | O5: 44286
A6: Revenue from Operations | B6: 27781 | C6: 26780 | D6: 25389 | E6: 27578 | F6: 30773 | G6: 27176.4 | I6: Revenue from Operations | J6: =B6/$G6 -> 1.0222472 | K6: =C6/$G6 -> 0.98541381 | L6: =D6/$G6 -> 0.9342297 | M6: =E6/$G6 -> 1.0147775 | N6: =F6/$G6 -> 1.1323428 | O6: =G6/$G6 -> 1
A7: Other Income | B7: 576 | C7: 426 | D7: 335 | E7: 74 | F7: 34 | G7: 47.8 | I7: Other Income | J7: =B7/$G7 -> 12.050209 | K7: =C7/$G7 -> 8.9121339 | L7: =D7/$G7 -> 7.0083682 | M7: =E7/$G7 -> 1.5481172 | N7: =F7/$G7 -> 0.71129707 | O7: =G7/$G7 -> 1
A8: Total Income | B8: =SUM(B6:B7) -> 28357 | C8: =SUM(C6:C7) -> 27206 | D8: =SUM(D6:D7) -> 25724 | E8: =SUM(E6:E7) -> 27652 | F8: =SUM(F6:F7) -> 30807 | G8: =SUM(G6:G7) -> 27224.2 | I8: Total Income | J8: =B8/$G8 -> 1.04161 | K8: =C8/$G8 -> 0.99933148 | L8: =D8/$G8 -> 0.94489462 | M8: =E8/$G8 -> 1.015714 | N8: =F8/$G8 -> 1.1316035 | O8: =G8/$G8 -> 1
A10: Expenses | I10: Expenses
A11: Cost of materials consumed | B11: 5998 | C11: 5443 | D11: 5254 | E11: 5337 | F11: 4789 | G11: 3988.6 | I11: Cost of materials consumed | J11: =B11/$G11 -> 1.5037858 | K11: =C11/$G11 -> 1.3646392 | L11: =D11/$G11 -> 1.3172542 | M11: =E11/$G11 -> 1.3380635 | N11: =F11/$G11 -> 1.2006719 | O11: =G11/$G11 -> 1
A12: Purchase of stock-in-trade | B12: 808 | C12: 864 | D12: 675 | E12: 864 | F12: 577 | G12: 349.4 | I12: Purchase of stock-in-trade | J12: =B12/$G12 -> 2.3125358 | K12: =C12/$G12 -> 2.4728105 | L12: =D12/$G12 -> 1.9318832 | M12: =E12/$G12 -> 2.4728105 | N12: =F12/$G12 -> 1.6514024 | O12: =G12/$G12 -> 1
A13: Change in inventories of finished goods, work-in-progress and stock-in-trade | B13: -140 | C13: 90 | D13: 119 | E13: -129 | F13: -82.8 | G13: 130.2 | I13: Change in inventories of finished goods, work-in-progress and stock-in-trade | J13: =B13/$G13 -> -1.0752688 | K13: =C13/$G13 -> 0.69124424 | L13: =D13/$G13 -> 0.91397849 | M13: =E13/$G13 -> -0.99078341 | N13: =F13/$G13 -> -0.6359447 | O13: =G13/$G13 -> 1
A14: Excise duty | B14: 15333 | C14: 15207 | D14: 14697 | E14: 17204 | F14: 21349 | G14: 19287.2 | I14: Excise duty | J14: =B14/$G14 -> 0.7949832 | K14: =C14/$G14 -> 0.78845037 | L14: =D14/$G14 -> 0.76200796 | M14: =E14/$G14 -> 0.89199054 | N14: =F14/$G14 -> 1.1068999 | O14: =G14/$G14 -> 1
A15: Employee benefits expense | B15: 623 | C15: 605 | D15: 543 | E15: 607 | F15: 650 | G15: 540.4 | I15: Employee benefits expense | J15: =B15/$G15 -> 1.1528497 | K15: =C15/$G15 -> 1.1195411 | L15: =D15/$G15 -> 1.0048113 | M15: =E15/$G15 -> 1.123242 | N15: =F15/$G15 -> 1.2028127 | O15: =G15/$G15 -> 1
A16: Advertisement and sales promotion | B16: 1295 | C16: 1128 | D16: 1041 | E16: 920 | F16: 689 | G16: 571.6 | I16: Advertisement and sales promotion | J16: =B16/$G16 -> 2.2655703 | K16: =C16/$G16 -> 1.973408 | L16: =D16/$G16 -> 1.8212036 | M16: =E16/$G16 -> 1.6095171 | N16: =F16/$G16 -> 1.2053884 | O16: =G16/$G16 -> 1
A17: Other expenses | B17: 1568 | C17: 1385 | D17: 1352 | E17: 1356 | F17: 1303 | G17: 1272.9 | I17: Other expenses | J17: =B17/$G17 -> 1.2318328 | K17: =C17/$G17 -> 1.0880666 | L17: =D17/$G17 -> 1.0621416 | M17: =E17/$G17 -> 1.065284 | N17: =F17/$G17 -> 1.0236468 | O17: =G17/$G17 -> 1
A18: Total expenses | B18: =SUM(B11:B17) -> 25485 | C18: =SUM(C11:C17) -> 24722 | D18: =SUM(D11:D17) -> 23681 | E18: =SUM(E11:E17) -> 26159 | F18: =SUM(F11:F17) -> 29274.2 | G18: =SUM(G11:G17) -> 26140.3 | I18: Total expenses | J18: =B18/$G18 -> 0.97493143 | K18: =C18/$G18 -> 0.94574278 | L18: =D18/$G18 -> 0.90591921 | M18: =E18/$G18 -> 1.0007154 | N18: =F18/$G18 -> 1.1198877 | O18: =G18/$G18 -> 1
A20: EBITDA | B20: =B8-B18 -> 2872 | C20: =C8-C18 -> 2484 | D20: =D8-D18 -> 2043 | E20: =E8-E18 -> 1493 | F20: =F8-F18 -> 1532.8 | G20: =G8-G18 -> 1083.9 | I20: EBITDA | J20: =B20/$G20 -> 2.6496909 | K20: =C20/$G20 -> 2.2917243 | L20: =D20/$G20 -> 1.8848602 | M20: =E20/$G20 -> 1.3774333 | N20: =F20/$G20 -> 1.4141526 | O20: =G20/$G20 -> 1
A21: Depreciation and amortisation expense | B21: 283 | C21: 274 | D21: 264 | E21: 271 | F21: 289 | G21: 249.3 | I21: Depreciation and amortisation expense | J21: =B21/$G21 -> 1.1351785 | K21: =C21/$G21 -> 1.0990774 | L21: =D21/$G21 -> 1.0589651 | M21: =E21/$G21 -> 1.0870437 | N21: =F21/$G21 -> 1.1592459 | O21: =G21/$G21 -> 1
A22: EBIT | B22: =B20-B21 -> 2589 | C22: =C20-C21 -> 2210 | D22: =D20-D21 -> 1779 | E22: =E20-E21 -> 1222 | F22: =F20-F21 -> 1243.8 | G22: =G20-G21 -> 834.6 | I22: EBIT | J22: =B22/$G22 -> 3.1020848 | K22: =C22/$G22 -> 2.6479751 | L22: =D22/$G22 -> 2.13156 | M22: =E22/$G22 -> 1.4641745 | N22: =F22/$G22 -> 1.4902948 | O22: =G22/$G22 -> 1
A23: Finance costs | B23: 158 | C23: 89 | D23: 76 | E23: 104 | F23: 88 | G23: 165.8 | I23: Finance costs | J23: =B23/$G23 -> 0.95295537 | K23: =C23/$G23 -> 0.53679131 | L23: =D23/$G23 -> 0.45838359 | M23: =E23/$G23 -> 0.62726176 | N23: =F23/$G23 -> 0.53075995 | O23: =G23/$G23 -> 1
A24: PBT before profits of JVs | B24: =B22-B23 -> 2431 | C24: =C22-C23 -> 2121 | D24: =D22-D23 -> 1703 | E24: =E22-E23 -> 1118 | F24: =F22-F23 -> 1155.8 | G24: =G22-G23 -> 668.8 | I24: PBT before profits of JVs | J24: =B24/$G24 -> 3.6348684 | K24: =C24/$G24 -> 3.1713517 | L24: =D24/$G24 -> 2.5463517 | M24: =E24/$G24 -> 1.6716507 | N24: =F24/$G24 -> 1.7281699 | O24: =G24/$G24 -> 1
A25: Add: Share of Profits of JVs | B25: 0 | C25: 0 | D25: 0 | E25: 0 | F25: 0 | G25: 0 | I25: Add: Share of Profits of JVs
A26: PBT & Exceptional Items | B26: =SUM(B24:B25) -> 2431 | C26: =SUM(C24:C25) -> 2121 | D26: =SUM(D24:D25) -> 1703 | E26: =SUM(E24:E25) -> 1118 | F26: =SUM(F24:F25) -> 1155.8 | G26: =SUM(G24:G25) -> 668.8 | I26: PBT & Exceptional Items | J26: =B26/$G26 -> 3.6348684 | K26: =C26/$G26 -> 3.1713517 | L26: =D26/$G26 -> 2.5463517 | M26: =E26/$G26 -> 1.6716507 | N26: =F26/$G26 -> 1.7281699 | O26: =G26/$G26 -> 1
A27: Exceptional Items | B27: -91 | C27: -65 | D27: -17 | E27: 171 | F27: -156 | G27: -151.4 | I27: Exceptional Items | J27: =B27/$G27 -> 0.6010568 | K27: =C27/$G27 -> 0.42932629 | L27: =D27/$G27 -> 0.11228534 | M27: =E27/$G27 -> -1.1294584 | N27: =F27/$G27 -> 1.0303831 | O27: =G27/$G27 -> 1
A28: PBT | B28: =B26+B27 -> 2340 | C28: =C26+C27 -> 2056 | D28: =D26+D27 -> 1686 | E28: =E26+E27 -> 1289 | F28: =F26+F27 -> 999.8 | G28: =G26+G27 -> 517.4 | I28: PBT | J28: =B28/$G28 -> 4.5226131 | K28: =C28/$G28 -> 3.9737147 | L28: =D28/$G28 -> 3.2586007 | M28: =E28/$G28 -> 2.4913027 | N28: =F28/$G28 -> 1.9323541 | O28: =G28/$G28 -> 1
A29: Tax | B29: 510 | C29: 498 | D29: 374 | E29: 237 | F29: 160 | G29: 158.7 | I29: Tax | J29: =B29/$G29 -> 3.2136106 | K29: =C29/$G29 -> 3.1379962 | L29: =D29/$G29 -> 2.3566478 | M29: =E29/$G29 -> 1.4933837 | N29: =F29/$G29 -> 1.0081916 | O29: =G29/$G29 -> 1
A30: PAT | B30: =B28-B29 -> 1830 | C30: =C28-C29 -> 1558 | D30: =D28-D29 -> 1312 | E30: =E28-E29 -> 1052 | F30: =F28-F29 -> 839.8 | G30: =G28-G29 -> 358.7 | I30: PAT | J30: =B30/$G30 -> 5.1017563 | K30: =C30/$G30 -> 4.3434625 | L30: =D30/$G30 -> 3.6576526 | M30: =E30/$G30 -> 2.9328129 | N30: =F30/$G30 -> 2.3412322 | O30: =G30/$G30 -> 1
A31: Less: Share of Minority Interest | B31: 0 | C31: 0 | D31: 0 | E31: 0 | F31: 0 | G31: 0 | I31: Less: Share of Minority Interest
A32: PAT for Equity Shareholders | B32: =B30-B31 -> 1830 | C32: =C30-C31 -> 1558 | D32: =D30-D31 -> 1312 | E32: =E30-E31 -> 1052 | F32: =F30-F31 -> 839.8 | G32: =G30-G31 -> 358.7 | I32: PAT for Equity Shareholders | J32: =B32/$G32 -> 5.1017563 | K32: =C32/$G32 -> 4.3434625 | L32: =D32/$G32 -> 3.6576526 | M32: =E32/$G32 -> 2.9328129 | N32: =F32/$G32 -> 2.3412322 | O32: =G32/$G32 -> 1
A33: Dividend | B33: 1263 | C33: 350 | D33: 291 | E33: 0 | F33: 0 | G33: 0 | I33: Dividend
A34: Tax Rate (%) | B34: =B29/B28 -> 0.21794872 | C34: =C29/C28 -> 0.2422179 | D34: =D29/D28 -> 0.22182681 | E34: =E29/E28 -> 0.18386346 | F34: =F29/F28 -> 0.16003201 | G34: =G29/G28 -> 0.30672594 | I34: Tax Rate (%)
A37: Balance Sheet | I37: Balance Sheet
A38: Particulars | B38: 46112 | C38: 45747 | D38: 45382 | E38: 45016 | F38: 44651 | G38: 44286 | I38: Particulars | J38: 46112 | K38: 45747 | L38: 45382 | M38: 45016 | N38: 44651 | O38: 44286
A39: Equity & Liabilities | I39: Equity & Liabilities
A40: Share capital | B40: 145 | C40: 145 | D40: 145 | E40: 145.5 | F40: 145.5 | G40: 145.3 | I40: Share capital | J40: =B40/$G40 -> 0.99793531 | K40: =C40/$G40 -> 0.99793531 | L40: =D40/$G40 -> 0.99793531 | M40: =E40/$G40 -> 1.0013765 | N40: =F40/$G40 -> 1.0013765 | O40: =G40/$G40 -> 1
A41: Share suspense | B41: 0 | C41: 0 | D41: 0 | E41: 0 | F41: 0.2 | G41: 0 | I41: Share suspense
A42: Other equity | I42: Other equity
A43: Reserves and surplus | B43: 8576 | C43: 7734 | D43: 6818 | E43: 5799 | F43: 4746.8 | G43: 3981.5 | I43: Reserves and surplus | J43: =B43/$G43 -> 2.1539621 | K43: =C43/$G43 -> 1.942484 | L43: =D43/$G43 -> 1.7124199 | M43: =E43/$G43 -> 1.4564862 | N43: =F43/$G43 -> 1.192214 | O43: =G43/$G43 -> 1
A44: Total Equity | B44: =SUM(B40:B43) -> 8721 | C44: =SUM(C40:C43) -> 7879 | D44: =SUM(D40:D43) -> 6963 | E44: =SUM(E40:E43) -> 5944.5 | F44: =SUM(F40:F43) -> 4892.5 | G44: =SUM(G40:G43) -> 4126.8 | I44: Total Equity | J44: =B44/$G44 -> 2.1132597 | K44: =C44/$G44 -> 1.9092275 | L44: =D44/$G44 -> 1.6872637 | M44: =E44/$G44 -> 1.4404623 | N44: =F44/$G44 -> 1.1855433 | O44: =G44/$G44 -> 1
A46: Non-Current Liabilities | I46: Non-Current Liabilities
A47: Borrowings | B47: 0 | C47: 0 | D47: 0 | E47: 0.3 | F47: 0.9 | G47: 0 | I47: Borrowings
A48: Lease liabilities | B48: 307 | C48: 334 | D48: 137 | E48: 80 | F48: 134.1 | G48: 92.5 | I48: Lease liabilities | J48: =B48/$G48 -> 3.3189189 | K48: =C48/$G48 -> 3.6108108 | L48: =D48/$G48 -> 1.4810811 | M48: =E48/$G48 -> 0.86486486 | N48: =F48/$G48 -> 1.4497297 | O48: =G48/$G48 -> 1
A49: Provisions | B49: 39 | C49: 16 | D49: 15 | E49: 12.3 | F49: 14.9 | G49: 7.5 | I49: Provisions | J49: =B49/$G49 -> 5.2 | K49: =C49/$G49 -> 2.1333333 | L49: =D49/$G49 -> 2 | M49: =E49/$G49 -> 1.64 | N49: =F49/$G49 -> 1.9866667 | O49: =G49/$G49 -> 1
A50: Total Non-Current Liabilities | B50: =SUM(B47:B49) -> 346 | C50: =SUM(C47:C49) -> 350 | D50: =SUM(D47:D49) -> 152 | E50: =SUM(E47:E49) -> 92.6 | F50: =SUM(F47:F49) -> 149.9 | G50: =SUM(G47:G49) -> 100 | I50: Total Non-Current Liabilities | J50: =B50/$G50 -> 3.46 | K50: =C50/$G50 -> 3.5 | L50: =D50/$G50 -> 1.52 | M50: =E50/$G50 -> 0.926 | N50: =F50/$G50 -> 1.499 | O50: =G50/$G50 -> 1
B51: 98 | C51: 146 | D51: 103 | E51: 102.2 | F51: 129.6
A52: Current Liabilities | I52: Current Liabilities
A53: Borrowings | B53: 0 | C53: 0 | D53: 0.8 | E53: 0.8 | F53: 340.8 | G53: 555.6 | I53: Borrowings | J53: =B53/$G53 -> 0 | K53: =C53/$G53 -> 0 | L53: =D53/$G53 -> 0.0014398848 | M53: =E53/$G53 -> 0.0014398848 | N53: =F53/$G53 -> 0.61339093 | O53: =G53/$G53 -> 1
A54: Lease liabilities | B54: 98 | C54: 146 | D54: 103 | E54: 102.2 | F54: 129.6 | G54: 65.3 | I54: Lease liabilities | J54: =B54/$G54 -> 1.5007657 | K54: =C54/$G54 -> 2.2358346 | L54: =D54/$G54 -> 1.5773354 | M54: =E54/$G54 -> 1.5650842 | N54: =F54/$G54 -> 1.9846861 | O54: =G54/$G54 -> 1
A55: Trade payables - MSME | B55: 140 | C55: 74 | D55: 69 | E55: 50.2 | F55: 79.2 | G55: 64 | I55: Trade payables - MSME | J55: =B55/$G55 -> 2.1875 | K55: =C55/$G55 -> 1.15625 | L55: =D55/$G55 -> 1.078125 | M55: =E55/$G55 -> 0.784375 | N55: =F55/$G55 -> 1.2375 | O55: =G55/$G55 -> 1
A56: Trade payables - other creditors | B56: 2237 | C56: 2078 | D56: 1758 | E56: 1688.1 | F56: 1448.7 | G56: 1317.3 | I56: Trade payables - other creditors | J56: =B56/$G56 -> 1.6981705 | K56: =C56/$G56 -> 1.5774691 | L56: =D56/$G56 -> 1.3345479 | M56: =E56/$G56 -> 1.2814849 | N56: =F56/$G56 -> 1.0997495 | O56: =G56/$G56 -> 1
A57: Other financial liabilities | B57: 269 | C57: 484 | D57: 204 | E57: 284.6 | F57: 192.6 | G57: 192.1 | I57: Other financial liabilities | J57: =B57/$G57 -> 1.4003123 | K57: =C57/$G57 -> 2.5195211 | L57: =D57/$G57 -> 1.0619469 | M57: =E57/$G57 -> 1.48152 | N57: =F57/$G57 -> 1.0026028 | O57: =G57/$G57 -> 1
A58: Provisions | B58: 500 | C58: 373 | D58: 367 | E58: 371.5 | F58: 485.9 | G58: 537.9 | I58: Provisions | J58: =B58/$G58 -> 0.92954081 | K58: =C58/$G58 -> 0.69343744 | L58: =D58/$G58 -> 0.68228295 | M58: =E58/$G58 -> 0.69064882 | N58: =F58/$G58 -> 0.90332776 | O58: =G58/$G58 -> 1
A59: Current tax liabilities (net) | B59: 571 | C59: 358 | D59: 324 | E59: 282.9 | F59: 190.4 | G59: 322.5 | I59: Current tax liabilities (net) | J59: =B59/$G59 -> 1.7705426 | K59: =C59/$G59 -> 1.1100775 | L59: =D59/$G59 -> 1.0046512 | M59: =E59/$G59 -> 0.8772093 | N59: =F59/$G59 -> 0.5903876 | O59: =G59/$G59 -> 1
A60: Other current liabilities | B60: 982 | C60: 976 | D60: 802 | E60: 754 | F60: 813.3 | G60: 859.7 | I60: Other current liabilities | J60: =B60/$G60 -> 1.1422589 | K60: =C60/$G60 -> 1.1352797 | L60: =D60/$G60 -> 0.93288356 | M60: =E60/$G60 -> 0.87705013 | N60: =F60/$G60 -> 0.94602768 | O60: =G60/$G60 -> 1
A61: Total Current Liabilities | B61: =SUM(B53:B60) -> 4797 | C61: =SUM(C53:C60) -> 4489 | D61: =SUM(D53:D60) -> 3627.8 | E61: =SUM(E53:E60) -> 3534.3 | F61: =SUM(F53:F60) -> 3680.5 | G61: =SUM(G53:G60) -> 3914.4 | I61: Total Current Liabilities | J61: =B61/$G61 -> 1.2254752 | K61: =C61/$G61 -> 1.1467913 | L61: =D61/$G61 -> 0.92678316 | M61: =E61/$G61 -> 0.902897 | N61: =F61/$G61 -> 0.94024627 | O61: =G61/$G61 -> 1
A62: TOTAL EQUITIES & LIABILITIES | B62: =SUM(B44+B50+B61) -> 13864 | C62: =SUM(C44+C50+C61) -> 12718 | D62: =SUM(D44+D50+D61) -> 10742.8 | E62: =SUM(E44+E50+E61) -> 9571.4 | F62: =SUM(F44+F50+F61) -> 8722.9 | G62: =SUM(G44+G50+G61) -> 8141.2 | I62: TOTAL EQUITIES & LIABILITIES | J62: =B62/$G62 -> 1.7029431 | K62: =C62/$G62 -> 1.5621776 | L62: =D62/$G62 -> 1.3195598 | M62: =E62/$G62 -> 1.1756743 | N62: =F62/$G62 -> 1.0714514 | O62: =G62/$G62 -> 1
A63: Assets | I63: Assets
A64: Non-Current Assets | I64: Non-Current Assets
A65: Property, plant and equipment | B65: 831 | C65: 850 | D65: 844 | E65: 978.3 | F65: 1201.4 | G65: 1104.8 | I65: Property, plant and equipment | J65: =B65/$G65 -> 0.75217234 | K65: =C65/$G65 -> 0.76937002 | L65: =D65/$G65 -> 0.76393917 | M65: =E65/$G65 -> 0.88549964 | N65: =F65/$G65 -> 1.0874366 | O65: =G65/$G65 -> 1
A66: Right-of-use assets | B66: 381 | C66: 457 | D66: 227 | E66: 172.6 | F66: 260.6 | G66: 164.4 | I66: Right-of-use assets | J66: =B66/$G66 -> 2.3175182 | K66: =C66/$G66 -> 2.7798054 | L66: =D66/$G66 -> 1.3807786 | M66: =E66/$G66 -> 1.0498783 | N66: =F66/$G66 -> 1.5851582 | O66: =G66/$G66 -> 1
A67: Capital work-in-progress | B67: 70 | C67: 72 | D67: 37 | E67: 66.8 | F67: 87.7 | G67: 78.1 | I67: Capital work-in-progress | J67: =B67/$G67 -> 0.89628681 | K67: =C67/$G67 -> 0.92189501 | L67: =D67/$G67 -> 0.4737516 | M67: =E67/$G67 -> 0.8553137 | N67: =F67/$G67 -> 1.1229193 | O67: =G67/$G67 -> 1
A68: Intangible assets | B68: 11 | C68: 24 | D68: 35 | E68: 31.2 | F68: 24.6 | G68: 31.6 | I68: Intangible assets | J68: =B68/$G68 -> 0.34810127 | K68: =C68/$G68 -> 0.75949367 | L68: =D68/$G68 -> 1.1075949 | M68: =E68/$G68 -> 0.98734177 | N68: =F68/$G68 -> 0.77848101 | O68: =G68/$G68 -> 1
A69: Intangible assets under development | D69: 0 | E69: 16 | F69: 8 | G69: 8.4 | I69: Intangible assets under development | J69: =B69/$G69 -> 0 | K69: =C69/$G69 -> 0 | L69: =D69/$G69 -> 0 | M69: =E69/$G69 -> 1.9047619 | N69: =F69/$G69 -> 0.95238095 | O69: =G69/$G69 -> 1
A70: Investment property | B70: 58 | C70: 75 | D70: 139 | E70: 25.3 | F70: 0 | G70: 0 | I70: Investment property
A71: Financial assets | I71: Financial assets
A72: Investments in subsidiaries and associate/joint ventures | B72: 301 | C72: 234 | D72: 224 | E72: 205.9 | F72: 216.9 | G72: 202.1 | I72: Investments in subsidiaries and associate/joint ventures | J72: =B72/$G72 -> 1.4893617 | K72: =C72/$G72 -> 1.1578427 | L72: =D72/$G72 -> 1.1083622 | M72: =E72/$G72 -> 1.0188026 | N72: =F72/$G72 -> 1.0732311 | O72: =G72/$G72 -> 1
A73: Trade receivables | B73: 351 | C73: 340 | D73: 365 | E73: 0 | F73: 0 | G73: 0 | I73: Trade receivables
A74: Loans | B74: 0 | C74: 0 | D74: 0 | E74: 0 | F74: 0 | G74: 174.2 | I74: Loans | J74: =B74/$G74 -> 0 | K74: =C74/$G74 -> 0 | L74: =D74/$G74 -> 0 | M74: =E74/$G74 -> 0 | N74: =F74/$G74 -> 0 | O74: =G74/$G74 -> 1
A75: Other financial assets | B75: 308 | C75: 384 | D75: 112 | E75: 146.2 | F75: 148.1 | G75: 79.2 | I75: Other financial assets | J75: =B75/$G75 -> 3.8888889 | K75: =C75/$G75 -> 4.8484848 | L75: =D75/$G75 -> 1.4141414 | M75: =E75/$G75 -> 1.8459596 | N75: =F75/$G75 -> 1.8699495 | O75: =G75/$G75 -> 1
A76: Deferred tax assets (net) | B76: 284 | C76: 155 | D76: 177 | E76: 157.3 | F76: 142.8 | G76: 171.1 | I76: Deferred tax assets (net) | J76: =B76/$G76 -> 1.659848 | K76: =C76/$G76 -> 0.90590298 | L76: =D76/$G76 -> 1.0344828 | M76: =E76/$G76 -> 0.91934541 | N76: =F76/$G76 -> 0.83459965 | O76: =G76/$G76 -> 1
A77: Current tax assets (net) (Non-current) | B77: 1191 | C77: 1095 | D77: 1348 | E77: 1311.4 | F77: 1208.7 | G77: 1036.7 | I77: Current tax assets (net) (Non-current) | J77: =B77/$G77 -> 1.1488377 | K77: =C77/$G77 -> 1.0562361 | L77: =D77/$G77 -> 1.3002797 | M77: =E77/$G77 -> 1.2649754 | N77: =F77/$G77 -> 1.1659111 | O77: =G77/$G77 -> 1
A78: Other non-current assets | B78: 274 | C78: 215 | D78: 216 | E78: 239.2 | F78: 234.2 | G78: 291.4 | I78: Other non-current assets | J78: =B78/$G78 -> 0.94028826 | K78: =C78/$G78 -> 0.73781743 | L78: =D78/$G78 -> 0.74124914 | M78: =E78/$G78 -> 0.82086479 | N78: =F78/$G78 -> 0.80370625 | O78: =G78/$G78 -> 1
A79: Total Non-Current Assets | B79: =SUM(B65:B78) -> 4060 | C79: =SUM(C65:C78) -> 3901 | D79: =SUM(D65:D78) -> 3724 | E79: =SUM(E65:E78) -> 3350.2 | F79: =SUM(F65:F78) -> 3533 | G79: =SUM(G65:G78) -> 3342 | I79: Total Non-Current Assets | J79: =B79/$G79 -> 1.2148414 | K79: =C79/$G79 -> 1.1672651 | L79: =D79/$G79 -> 1.1143028 | M79: =E79/$G79 -> 1.0024536 | N79: =F79/$G79 -> 1.0571514 | O79: =G79/$G79 -> 1
A81: Current Assets | I81: Current Assets
A82: Inventories | B82: 2659 | C82: 2305 | D82: 2063 | E82: 2230 | F82: 2164.3 | G82: 1981 | I82: Inventories | J82: =B82/$G82 -> 1.3422514 | K82: =C82/$G82 -> 1.1635538 | L82: =D82/$G82 -> 1.0413932 | M82: =E82/$G82 -> 1.1256941 | N82: =F82/$G82 -> 1.092529 | O82: =G82/$G82 -> 1
A83: Financial assets | I83: Financial assets
A84: Investments | B84: 1153 | C84: 873 | D84: 599 | E84: 255.8 | F84: 222.1 | G84: 0 | I84: Investments
A85: Trade receivables | B85: 3592 | C85: 3288 | D85: 2763 | E85: 2382.8 | F85: 2302.1 | G85: 2160.1 | I85: Trade receivables | J85: =B85/$G85 -> 1.662886 | K85: =C85/$G85 -> 1.5221518 | L85: =D85/$G85 -> 1.2791074 | M85: =E85/$G85 -> 1.1030971 | N85: =F85/$G85 -> 1.0657377 | O85: =G85/$G85 -> 1
A86: Cash and cash equivalents | B86: 855 | C86: 1150 | D86: 1021 | E86: 81.4 | F86: 27 | G86: 49.2 | I86: Cash and cash equivalents | J86: =B86/$G86 -> 17.378049 | K86: =C86/$G86 -> 23.373984 | L86: =D86/$G86 -> 20.752033 | M86: =E86/$G86 -> 1.6544715 | N86: =F86/$G86 -> 0.54878049 | O86: =G86/$G86 -> 1
A87: Bank balances other than cash and cash equivalents | B87: 1027 | C87: 623 | D87: 188 | E87: 76.8 | F87: 5.8 | G87: 6.1 | I87: Bank balances other than cash and cash equivalents | J87: =B87/$G87 -> 168.36066 | K87: =C87/$G87 -> 102.13115 | L87: =D87/$G87 -> 30.819672 | M87: =E87/$G87 -> 12.590164 | N87: =F87/$G87 -> 0.95081967 | O87: =G87/$G87 -> 1
A88: Loans | B88: 1 | C88: 22 | D88: 10 | E88: 108.7 | F88: 138.8 | G88: 100.5 | I88: Loans | J88: =B88/$G88 -> 0.0099502488 | K88: =C88/$G88 -> 0.21890547 | L88: =D88/$G88 -> 0.099502488 | M88: =E88/$G88 -> 1.081592 | N88: =F88/$G88 -> 1.3810945 | O88: =G88/$G88 -> 1
A89: Other financial assets | B89: 59 | C89: 259 | D89: 40 | E89: 136.5 | F89: 80.6 | G89: 204.7 | I89: Other financial assets | J89: =B89/$G89 -> 0.28822667 | K89: =C89/$G89 -> 1.2652662 | L89: =D89/$G89 -> 0.19540791 | M89: =E89/$G89 -> 0.66682951 | N89: =F89/$G89 -> 0.39374695 | O89: =G89/$G89 -> 1
A90: Other current assets | B90: 391 | C90: 297 | D90: 334 | E90: 257.8 | F90: 249 | G90: 297.6 | I90: Other current assets | J90: =B90/$G90 -> 1.3138441 | K90: =C90/$G90 -> 0.99798387 | L90: =D90/$G90 -> 1.1223118 | M90: =E90/$G90 -> 0.86626344 | N90: =F90/$G90 -> 0.83669355 | O90: =G90/$G90 -> 1
A91: Assets classified as held for sale | B91: 67 | C91: 0 | D91: 0 | E91: 0 | F91: 0 | G91: 0 | I91: Assets classified as held for sale
A92: Total Current Assets | B92: =SUM(B82:B91) -> 9804 | C92: =SUM(C82:C91) -> 8817 | D92: =SUM(D82:D91) -> 7018 | E92: =SUM(E82:E91) -> 5529.8 | F92: =SUM(F82:F91) -> 5189.7 | G92: =SUM(G82:G91) -> 4799.2 | I92: Total Current Assets | J92: =B92/$G92 -> 2.0428405 | K92: =C92/$G92 -> 1.8371812 | L92: =D92/$G92 -> 1.4623271 | M92: =E92/$G92 -> 1.1522337 | N92: =F92/$G92 -> 1.0813677 | O92: =G92/$G92 -> 1
A93: TOTAL ASSETS | B93: =SUM(B79,B92) -> 13864 | C93: =SUM(C79,C92) -> 12718 | D93: =SUM(D79,D92) -> 10742 | E93: =SUM(E79,E92) -> 8880 | F93: =SUM(F79,F92) -> 8722.7 | G93: =SUM(G79,G92) -> 8141.2 | I93: TOTAL ASSETS | J93: =B93/$G93 -> 1.7029431 | K93: =C93/$G93 -> 1.5621776 | L93: =D93/$G93 -> 1.3194615 | M93: =E93/$G93 -> 1.0907483 | N93: =F93/$G93 -> 1.0714268 | O93: =G93/$G93 -> 1
A97: Avg. receivables | B97: =(B85+C85)/2 -> 3440 | C97: =(C85+D85)/2 -> 3025.5 | D97: =(D85+E85)/2 -> 2572.9 | E97: =(E85+F85)/2 -> 2342.45 | F97: =(F85+G85)/2 -> 2231.1
A98: Avg. inventory | B98: =(B82+C82)/2 -> 2482 | C98: =(C82+D82)/2 -> 2184 | D98: =(D82+E82)/2 -> 2146.5 | E98: =(E82+F82)/2 -> 2197.15 | F98: =(F82+G82)/2 -> 2072.65
A99: Avg. payables | B99: =((B55+B56)+(C55+C56))/2 -> 2264.5 | C99: =((C55+C56)+(D55+D56))/2 -> 1989.5 | D99: =((D55+D56)+(E55+E56))/2 -> 1782.65 | E99: =((E55+E56)+(F55+F56))/2 -> 1633.1 | F99: =((F55+F56)+(G55+G56))/2 -> 1454.6
A100: Avg. Total assets | B100: =(B93+C93)/2 -> 13291 | C100: =(C93+D93)/2 -> 11730 | D100: =(D93+E93)/2 -> 9811 | E100: =(E93+F93)/2 -> 8801.35 | F100: =(F93+G93)/2 -> 8431.95
A101: Working Capital | B101: =B92-B61 -> 5007 | C101: =C92-C61 -> 4328 | D101: =D92-D61 -> 3390.2 | E101: =E92-E61 -> 1995.5 | F101: =F92-F61 -> 1509.2
A102: Avg. Working Capital | B102: =(B101+C101)/2 -> 4667.5 | C102: =(C101+D101)/2 -> 3859.1 | D102: =(D101+E101)/2 -> 2692.85 | E102: =(E101+F101)/2 -> 1752.35 | F102: =(F101+G92-G61)/2 -> 1197
A103: Avg. Shareholder's Equity | B103: =(B44+C44)/2 -> 8300 | C103: =(C44+D44)/2 -> 7421 | D103: =(D44+E44)/2 -> 6453.75 | E103: =(E44+F44)/2 -> 5418.5 | F103: =(F44+G44)/2 -> 4509.65
A105: Ratios
A106: Liquidity Measures | B106: 46112 | C106: 45747 | D106: 45382 | E106: 45016 | F106: 44651
A107: Current Ratio (CA/CL) | B107: =B92/B61 -> 2.0437774 | C107: =C92/C61 -> 1.9641346 | D107: =D92/D61 -> 1.9345058 | E107: =E92/E61 -> 1.5646097 | F107: =F92/F61 -> 1.410053
A108: Quick Ratio (CA-Invent.-Prepaid Exp/CL) | B108: =(B92-B82)/B61 -> 1.4894726 | C108: =(C92-C82)/C61 -> 1.4506572 | D108: =(D92-D82)/D61 -> 1.3658416 | E108: =(E92-E82)/E61 -> 0.93365023 | F108: =(F92-F82)/F61 -> 0.82200788
A109: Cash Ratio (Cash and equivalents/CL) | B109: =(B86+B87)/B61 -> 0.39232854 | C109: =(C86+C87)/C61 -> 0.39496547 | D109: =(D86+D87)/D61 -> 0.33325983 | E109: =(E86+E87)/E61 -> 0.044761339 | F109: =(F86+F87)/F61 -> 0.0089118326
A111: Leverage Measures | B111: 46112 | C111: 45747 | D111: 45382 | E111: 45016 | F111: 44651
A112: Total Debt to Total Assets [(CL+LTD+OL)/Avg. TA] | B112: =(B61+B50)/B100 -> 0.38695358 | C112: =(C61+C50)/C100 -> 0.41253197 | D112: =(D61+D50)/D100 -> 0.38526144 | E112: =(E61+E50)/E100 -> 0.41208451 | F112: =(F61+F50)/F100 -> 0.45427214
A113: Long term Debt to Equity Ratio (LTD+OL)/Avg. SE) | B113: =B50/B103 -> 0.041686747 | C113: =C50/C103 -> 0.047163455 | D113: =D50/D103 -> 0.023552198 | E113: =E50/E103 -> 0.0170896 | F113: =F50/F103 -> 0.03323983
...

Sheet Sheet1
A1: 44651 | B1: 45016 | C1: 45382 | D1: 45747 | E1: 46112
A2: 30773 | B2: 27578 | C2: 25389 | D2: 26780 | E2: 27781
A3: 34 | B3: 74 | C3: 335 | D3: 426 | E3: 576
A4: =SUM(A2:A3) -> 30807 | B4: =SUM(B2:B3) -> 27652 | C4: =SUM(C2:C3) -> 25724 | D4: =SUM(D2:D3) -> 27206 | E4: =SUM(E2:E3) -> 28357
A7: 4789 | B7: 5337 | C7: 5254 | D7: 5443 | E7: 5998
A8: 577 | B8: 864 | C8: 675 | D8: 864 | E8: 808
A9: -82.8 | B9: -129 | C9: 119 | D9: 90 | E9: -140
A10: 21349 | B10: 17204 | C10: 14697 | D10: 15207 | E10: 15333
A11: 650 | B11: 607 | C11: 543 | D11: 605 | E11: 623
A12: 689 | B12: 920 | C12: 1041 | D12: 1128 | E12: 1295
A13: 1303 | B13: 1356 | C13: 1352 | D13: 1385 | E13: 1568
A14: =SUM(A7:A13) -> 29274.2 | B14: =SUM(B7:B13) -> 26159 | C14: =SUM(C7:C13) -> 23681 | D14: =SUM(D7:D13) -> 24722 | E14: =SUM(E7:E13) -> 25485
A16: =A4-A14 -> 1532.8 | B16: =B4-B14 -> 1493 | C16: =C4-C14 -> 2043 | D16: =D4-D14 -> 2484 | E16: =E4-E14 -> 2872
A17: 289 | B17: 271 | C17: 264 | D17: 274 | E17: 283
A18: =A16-A17 -> 1243.8 | B18: =B16-B17 -> 1222 | C18: =C16-C17 -> 1779 | D18: =D16-D17 -> 2210 | E18: =E16-E17 -> 2589
A19: 88 | B19: 104 | C19: 76 | D19: 89 | E19: 158
A20: =A18-A19 -> 1155.8 | B20: =B18-B19 -> 1118 | C20: =C18-C19 -> 1703 | D20: =D18-D19 -> 2121 | E20: =E18-E19 -> 2431
A21: 0 | B21: 0 | C21: 0 | D21: 0 | E21: 0
A22: =SUM(A20:A21) -> 1155.8 | B22: =SUM(B20:B21) -> 1118 | C22: =SUM(C20:C21) -> 1703 | D22: =SUM(D20:D21) -> 2121 | E22: =SUM(E20:E21) -> 2431
A23: -156 | B23: 171 | C23: -17 | D23: -65 | E23: -91
A24: =A22+A23 -> 999.8 | B24: =B22+B23 -> 1289 | C24: =C22+C23 -> 1686 | D24: =D22+D23 -> 2056 | E24: =E22+E23 -> 2340
A25: 160 | B25: 237 | C25: 374 | D25: 498 | E25: 510
A26: =A24-A25 -> 839.8 | B26: =B24-B25 -> 1052 | C26: =C24-C25 -> 1312 | D26: =D24-D25 -> 1558 | E26: =E24-E25 -> 1830
A27: 0 | B27: 0 | C27: 0 | D27: 0 | E27: 0
A28: =A26-A27 -> 839.8 | B28: =B26-B27 -> 1052 | C28: =C26-C27 -> 1312 | D28: =D26-D27 -> 1558 | E28: =E26-E27 -> 1830
A29: 0 | B29: 0 | C29: 291 | D29: 350 | E29: 1263
A30: =A25/A24 -> 0.16003201 | B30: =B25/B24 -> 0.18386346 | C30: =C25/C24 -> 0.22182681 | D30: =D25/D24 -> 0.2422179 | E30: =E25/E24 -> 0.21794872

Sheet Common Size FS
A2: Common Size statement
A4: Income Statement
A5: Particulars | B5: 46112 | C5: 45747 | D5: 45382 | E5: 45016 | F5: 44651 | G5: 44286
A6: Revenue from Operations | B6: ='FS & Trend Analysis'!B6/'FS & Trend Analysis'!B$6 -> 1 | C6: ='FS & Trend Analysis'!C6/'FS & Trend Analysis'!C$6 -> 1 | D6: ='FS & Trend Analysis'!D6/'FS & Trend Analysis'!D$6 -> 1 | E6: ='FS & Trend Analysis'!E6/'FS & Trend Analysis'!E$6 -> 1 | F6: ='FS & Trend Analysis'!F6/'FS & Trend Analysis'!F$6 -> 1 | G6: ='FS & Trend Analysis'!G6/'FS & Trend Analysis'!G$6 -> 1
A7: Other Income | B7: ='FS & Trend Analysis'!B7/'FS & Trend Analysis'!B$6 -> 0.020733595 | C7: ='FS & Trend Analysis'!C7/'FS & Trend Analysis'!C$6 -> 0.015907394 | D7: ='FS & Trend Analysis'!D7/'FS & Trend Analysis'!D$6 -> 0.013194691 | E7: ='FS & Trend Analysis'!E7/'FS & Trend Analysis'!E$6 -> 0.0026832983 | F7: ='FS & Trend Analysis'!F7/'FS & Trend Analysis'!F$6 -> 0.0011048647 | G7: ='FS & Trend Analysis'!G7/'FS & Trend Analysis'!G$6 -> 0.001758879
A8: Total Income | B8: ='FS & Trend Analysis'!B8/'FS & Trend Analysis'!B$6 -> 1.0207336 | C8: ='FS & Trend Analysis'!C8/'FS & Trend Analysis'!C$6 -> 1.0159074 | D8: ='FS & Trend Analysis'!D8/'FS & Trend Analysis'!D$6 -> 1.0131947 | E8: ='FS & Trend Analysis'!E8/'FS & Trend Analysis'!E$6 -> 1.0026833 | F8: ='FS & Trend Analysis'!F8/'FS & Trend Analysis'!F$6 -> 1.0011049 | G8: ='FS & Trend Analysis'!G8/'FS & Trend Analysis'!G$6 -> 1.0017589
A10: Expenses
A11: Raw Material | B11: ='FS & Trend Analysis'!B11/'FS & Trend Analysis'!B$6 -> 0.21590296 | C11: ='FS & Trend Analysis'!C11/'FS & Trend Analysis'!C$6 -> 0.20324869 | D11: ='FS & Trend Analysis'!D11/'FS & Trend Analysis'!D$6 -> 0.20694001 | E11: ='FS & Trend Analysis'!E11/'FS & Trend Analysis'!E$6 -> 0.19352382 | F11: ='FS & Trend Analysis'!F11/'FS & Trend Analysis'!F$6 -> 0.15562344 | G11: ='FS & Trend Analysis'!G11/'FS & Trend Analysis'!G$6 -> 0.14676705
A12: Excise Duty | B12: ='FS & Trend Analysis'!B12/'FS & Trend Analysis'!B$6 -> 0.029084626 | C12: ='FS & Trend Analysis'!C12/'FS & Trend Analysis'!C$6 -> 0.032262883 | D12: ='FS & Trend Analysis'!D12/'FS & Trend Analysis'!D$6 -> 0.026586317 | E12: ='FS & Trend Analysis'!E12/'FS & Trend Analysis'!E$6 -> 0.03132932 | F12: ='FS & Trend Analysis'!F12/'FS & Trend Analysis'!F$6 -> 0.018750203 | G12: ='FS & Trend Analysis'!G12/'FS & Trend Analysis'!G$6 -> 0.012856743
A13: Employee Costs | B13: ='FS & Trend Analysis'!B13/'FS & Trend Analysis'!B$6 -> -0.0050394154 | C13: ='FS & Trend Analysis'!C13/'FS & Trend Analysis'!C$6 -> 0.003360717 | D13: ='FS & Trend Analysis'!D13/'FS & Trend Analysis'!D$6 -> 0.0046870692 | E13: ='FS & Trend Analysis'!E13/'FS & Trend Analysis'!E$6 -> -0.0046776416 | F13: ='FS & Trend Analysis'!F13/'FS & Trend Analysis'!F$6 -> -0.0026906704 | G13: ='FS & Trend Analysis'!G13/'FS & Trend Analysis'!G$6 -> 0.0047909215
A14: Other Expenses | B14: ='FS & Trend Analysis'!B14/'FS & Trend Analysis'!B$6 -> 0.55192398 | C14: ='FS & Trend Analysis'!C14/'FS & Trend Analysis'!C$6 -> 0.56784914 | D14: ='FS & Trend Analysis'!D14/'FS & Trend Analysis'!D$6 -> 0.57887274 | E14: ='FS & Trend Analysis'!E14/'FS & Trend Analysis'!E$6 -> 0.62383059 | F14: ='FS & Trend Analysis'!F14/'FS & Trend Analysis'!F$6 -> 0.69375751 | G14: ='FS & Trend Analysis'!G14/'FS & Trend Analysis'!G$6 -> 0.70970401
A15: Total Expenses | B15: ='FS & Trend Analysis'!B15/'FS & Trend Analysis'!B$6 -> 0.022425399 | C15: ='FS & Trend Analysis'!C15/'FS & Trend Analysis'!C$6 -> 0.022591486 | D15: ='FS & Trend Analysis'!D15/'FS & Trend Analysis'!D$6 -> 0.021387215 | E15: ='FS & Trend Analysis'!E15/'FS & Trend Analysis'!E$6 -> 0.022010298 | F15: ='FS & Trend Analysis'!F15/'FS & Trend Analysis'!F$6 -> 0.021122413 | G15: ='FS & Trend Analysis'!G15/'FS & Trend Analysis'!G$6 -> 0.0198849
B16: ='FS & Trend Analysis'!B16/'FS & Trend Analysis'!B$6 -> 0.046614593 | C16: ='FS & Trend Analysis'!C16/'FS & Trend Analysis'!C$6 -> 0.042120986 | D16: ='FS & Trend Analysis'!D16/'FS & Trend Analysis'!D$6 -> 0.041002009 | E16: ='FS & Trend Analysis'!E16/'FS & Trend Analysis'!E$6 -> 0.033359925 | F16: ='FS & Trend Analysis'!F16/'FS & Trend Analysis'!F$6 -> 0.022389757 | G16: ='FS & Trend Analysis'!G16/'FS & Trend Analysis'!G$6 -> 0.021032955
A17: EBITDA | B17: ='FS & Trend Analysis'!B17/'FS & Trend Analysis'!B$6 -> 0.056441453 | C17: ='FS & Trend Analysis'!C17/'FS & Trend Analysis'!C$6 -> 0.0517177 | D17: ='FS & Trend Analysis'!D17/'FS & Trend Analysis'!D$6 -> 0.053251408 | E17: ='FS & Trend Analysis'!E17/'FS & Trend Analysis'!E$6 -> 0.049169628 | F17: ='FS & Trend Analysis'!F17/'FS & Trend Analysis'!F$6 -> 0.042342313 | G17: ='FS & Trend Analysis'!G17/'FS & Trend Analysis'!G$6 -> 0.046838433
A18: Depreciation & Amortization | B18: ='FS & Trend Analysis'!B18/'FS & Trend Analysis'!B$6 -> 0.91735359 | C18: ='FS & Trend Analysis'!C18/'FS & Trend Analysis'!C$6 -> 0.92315161 | D18: ='FS & Trend Analysis'!D18/'FS & Trend Analysis'!D$6 -> 0.93272677 | E18: ='FS & Trend Analysis'!E18/'FS & Trend Analysis'!E$6 -> 0.94854594 | F18: ='FS & Trend Analysis'!F18/'FS & Trend Analysis'!F$6 -> 0.95129497 | G18: ='FS & Trend Analysis'!G18/'FS & Trend Analysis'!G$6 -> 0.96187501
A19: EBIT | B19: ='FS & Trend Analysis'!B19/'FS & Trend Analysis'!B$6 -> 0 | C19: ='FS & Trend Analysis'!C19/'FS & Trend Analysis'!C$6 -> 0 | D19: ='FS & Trend Analysis'!D19/'FS & Trend Analysis'!D$6 -> 0 | E19: ='FS & Trend Analysis'!E19/'FS & Trend Analysis'!E$6 -> 0 | F19: ='FS & Trend Analysis'!F19/'FS & Trend Analysis'!F$6 -> 0 | G19: ='FS & Trend Analysis'!G19/'FS & Trend Analysis'!G$6 -> 0
A20: Finance Expenses | B20: ='FS & Trend Analysis'!B20/'FS & Trend Analysis'!B$6 -> 0.10338001 | C20: ='FS & Trend Analysis'!C20/'FS & Trend Analysis'!C$6 -> 0.092755788 | D20: ='FS & Trend Analysis'!D20/'FS & Trend Analysis'!D$6 -> 0.080467919 | E20: ='FS & Trend Analysis'!E20/'FS & Trend Analysis'!E$6 -> 0.054137356 | F20: ='FS & Trend Analysis'!F20/'FS & Trend Analysis'!F$6 -> 0.049809898 | G20: ='FS & Trend Analysis'!G20/'FS & Trend Analysis'!G$6 -> 0.03988387
A21: PBT before profits of JVs | B21: ='FS & Trend Analysis'!B21/'FS & Trend Analysis'!B$6 -> 0.010186818 | C21: ='FS & Trend Analysis'!C21/'FS & Trend Analysis'!C$6 -> 0.010231516 | D21: ='FS & Trend Analysis'!D21/'FS & Trend Analysis'!D$6 -> 0.010398204 | E21: ='FS & Trend Analysis'!E21/'FS & Trend Analysis'!E$6 -> 0.0098266734 | F21: ='FS & Trend Analysis'!F21/'FS & Trend Analysis'!F$6 -> 0.0093913496 | G21: ='FS & Trend Analysis'!G21/'FS & Trend Analysis'!G$6 -> 0.0091734005
A22: Add: Share of Profits of JVs | B22: ='FS & Trend Analysis'!B22/'FS & Trend Analysis'!B$6 -> 0.09319319 | C22: ='FS & Trend Analysis'!C22/'FS & Trend Analysis'!C$6 -> 0.082524272 | D22: ='FS & Trend Analysis'!D22/'FS & Trend Analysis'!D$6 -> 0.070069715 | E22: ='FS & Trend Analysis'!E22/'FS & Trend Analysis'!E$6 -> 0.044310682 | F22: ='FS & Trend Analysis'!F22/'FS & Trend Analysis'!F$6 -> 0.040418549 | G22: ='FS & Trend Analysis'!G22/'FS & Trend Analysis'!G$6 -> 0.030710469
A23: PBT & Exceptional Items | B23: ='FS & Trend Analysis'!B23/'FS & Trend Analysis'!B$6 -> 0.0056873403 | C23: ='FS & Trend Analysis'!C23/'FS & Trend Analysis'!C$6 -> 0.0033233757 | D23: ='FS & Trend Analysis'!D23/'FS & Trend Analysis'!D$6 -> 0.0029934223 | E23: ='FS & Trend Analysis'!E23/'FS & Trend Analysis'!E$6 -> 0.0037711219 | F23: ='FS & Trend Analysis'!F23/'FS & Trend Analysis'!F$6 -> 0.0028596497 | G23: ='FS & Trend Analysis'!G23/'FS & Trend Analysis'!G$6 -> 0.0061008816
A24: Exceptional Items | B24: ='FS & Trend Analysis'!B24/'FS & Trend Analysis'!B$6 -> 0.087505849 | C24: ='FS & Trend Analysis'!C24/'FS & Trend Analysis'!C$6 -> 0.079200896 | D24: ='FS & Trend Analysis'!D24/'FS & Trend Analysis'!D$6 -> 0.067076293 | E24: ='FS & Trend Analysis'!E24/'FS & Trend Analysis'!E$6 -> 0.040539561 | F24: ='FS & Trend Analysis'!F24/'FS & Trend Analysis'!F$6 -> 0.037558899 | G24: ='FS & Trend Analysis'!G24/'FS & Trend Analysis'!G$6 -> 0.024609588
A25: PBT | B25: ='FS & Trend Analysis'!B25/'FS & Trend Analysis'!B$6 -> 0 | C25: ='FS & Trend Analysis'!C25/'FS & Trend Analysis'!C$6 -> 0 | D25: ='FS & Trend Analysis'!D25/'FS & Trend Analysis'!D$6 -> 0 | E25: ='FS & Trend Analysis'!E25/'FS & Trend Analysis'!E$6 -> 0 | F25: ='FS & Trend Analysis'!F25/'FS & Trend Analysis'!F$6 -> 0 | G25: ='FS & Trend Analysis'!G25/'FS & Trend Analysis'!G$6 -> 0
A26: Tax | B26: ='FS & Trend Analysis'!B26/'FS & Trend Analysis'!B$6 -> 0.087505849 | C26: ='FS & Trend Analysis'!C26/'FS & Trend Analysis'!C$6 -> 0.079200896 | D26: ='FS & Trend Analysis'!D26/'FS & Trend Analysis'!D$6 -> 0.067076293 | E26: ='FS & Trend Analysis'!E26/'FS & Trend Analysis'!E$6 -> 0.040539561 | F26: ='FS & Trend Analysis'!F26/'FS & Trend Analysis'!F$6 -> 0.037558899 | G26: ='FS & Trend Analysis'!G26/'FS & Trend Analysis'!G$6 -> 0.024609588
A27: PAT | B27: ='FS & Trend Analysis'!B27/'FS & Trend Analysis'!B$6 -> -0.00327562 | C27: ='FS & Trend Analysis'!C27/'FS & Trend Analysis'!C$6 -> -0.0024271845 | D27: ='FS & Trend Analysis'!D27/'FS & Trend Analysis'!D$6 -> -0.00066958131 | E27: ='FS & Trend Analysis'!E27/'FS & Trend Analysis'!E$6 -> 0.0062005947 | F27: ='FS & Trend Analysis'!F27/'FS & Trend Analysis'!F$6 -> -0.005069379 | G27: ='FS & Trend Analysis'!G27/'FS & Trend Analysis'!G$6 -> -0.0055710101
A28: Less: Share of Minority Interest | B28: ='FS & Trend Analysis'!B28/'FS & Trend Analysis'!B$6 -> 0.084230229 | C28: ='FS & Trend Analysis'!C28/'FS & Trend Analysis'!C$6 -> 0.076773712 | D28: ='FS & Trend Analysis'!D28/'FS & Trend Analysis'!D$6 -> 0.066406712 | E28: ='FS & Trend Analysis'!E28/'FS & Trend Analysis'!E$6 -> 0.046740155 | F28: ='FS & Trend Analysis'!F28/'FS & Trend Analysis'!F$6 -> 0.03248952 | G28: ='FS & Trend Analysis'!G28/'FS & Trend Analysis'!G$6 -> 0.019038578
... A30: Dividend | B30: ='FS & Trend Analysis'!B30/'FS & Trend Analysis'!B$6 -> 0.065872359 | C30: ='FS & Trend Analysis'!C30/'FS & Trend Analysis'!C$6 -> 0.058177745 | D30: ='FS & Trend Analysis'!D30/'FS & Trend Analysis'!D$6 -> 0.051675923 | E30: ='FS & Trend Analysis'!E30/'FS & Trend Analysis'!E$6 -> 0.038146349 | F30: ='FS & Trend Analysis'!F30/'FS & Trend Analysis'!F$6 -> 0.027290157 | G30: ='FS & Trend Analysis'!G30/'FS & Trend Analysis'!G$6 -> 0.013198952
A33: Balance Sheet
A34: Particulars | B34: 46112 | C34: 45747 | D34: 45382 | E34: 45016 | F34: 44651 | G34: 44286
A35: Equity & Liabilities
A36: Share capital | B36: ='FS & Trend Analysis'!B40/'FS & Trend Analysis'!B$62 -> 0.010458742 | C36: ='FS & Trend Analysis'!C40/'FS & Trend Analysis'!C$62 -> 0.011401164 | D36: ='FS & Trend Analysis'!D40/'FS & Trend Analysis'!D$62 -> 0.013497412 | E36: ='FS & Trend Analysis'!E40/'FS & Trend Analysis'!E$62 -> 0.015201538 | F36: ='FS & Trend Analysis'!F40/'FS & Trend Analysis'!F$62 -> 0.016680232 | G36: ='FS & Trend Analysis'!G40/'FS & Trend Analysis'!G$62 -> 0.017847492
A37: Share suspense | B37: ='FS & Trend Analysis'!B41/'FS & Trend Analysis'!B$62 -> 0 | C37: ='FS & Trend Analysis'!C41/'FS & Trend Analysis'!C$62 -> 0 | D37: ='FS & Trend Analysis'!D41/'FS & Trend Analysis'!D$62 -> 0 | E37: ='FS & Trend Analysis'!E41/'FS & Trend Analysis'!E$62 -> 0 | F37: ='FS & Trend Analysis'!F41/'FS & Trend Analysis'!F$62 -> 2.2928155e-05 | G37: ='FS & Trend Analysis'!G41/'FS & Trend Analysis'!G$62 -> 0
A38: Other equity | B38: ='FS & Trend Analysis'!B42/'FS & Trend Analysis'!B$62 -> 0 | C38: ='FS & Trend Analysis'!C42/'FS & Trend Analysis'!C$62 -> 0 | D38: ='FS & Trend Analysis'!D42/'FS & Trend Analysis'!D$62 -> 0 | E38: ='FS & Trend Analysis'!E42/'FS & Trend Analysis'!E$62 -> 0 | F38: ='FS & Trend Analysis'!F42/'FS & Trend Analysis'!F$62 -> 0 | G38: ='FS & Trend Analysis'!G42/'FS & Trend Analysis'!G$62 -> 0
A39: Reserves and surplus | B39: ='FS & Trend Analysis'!B43/'FS & Trend Analysis'!B$62 -> 0.6185805 | C39: ='FS & Trend Analysis'!C43/'FS & Trend Analysis'!C$62 -> 0.60811448 | D39: ='FS & Trend Analysis'!D43/'FS & Trend Analysis'!D$62 -> 0.63465763 | E39: ='FS & Trend Analysis'!E43/'FS & Trend Analysis'!E$62 -> 0.60586748 | F39: ='FS & Trend Analysis'!F43/'FS & Trend Analysis'!F$62 -> 0.54417682 | G39: ='FS & Trend Analysis'!G43/'FS & Trend Analysis'!G$62 -> 0.48905567
A40: Total Equity | B40: ='FS & Trend Analysis'!B44/'FS & Trend Analysis'!B$62 -> 0.62903924 | C40: ='FS & Trend Analysis'!C44/'FS & Trend Analysis'!C$62 -> 0.61951565 | D40: ='FS & Trend Analysis'!D44/'FS & Trend Analysis'!D$62 -> 0.64815504 | E40: ='FS & Trend Analysis'!E44/'FS & Trend Analysis'!E$62 -> 0.62106902 | F40: ='FS & Trend Analysis'!F44/'FS & Trend Analysis'!F$62 -> 0.56087998 | G40: ='FS & Trend Analysis'!G44/'FS & Trend Analysis'!G$62 -> 0.50690316
B41: ='FS & Trend Analysis'!B45/'FS & Trend Analysis'!B$62 -> 0 | C41: ='FS & Trend Analysis'!C45/'FS & Trend Analysis'!C$62 -> 0 | D41: ='FS & Trend Analysis'!D45/'FS & Trend Analysis'!D$62 -> 0 | E41: ='FS & Trend Analysis'!E45/'FS & Trend Analysis'!E$62 -> 0 | F41: ='FS & Trend Analysis'!F45/'FS & Trend Analysis'!F$62 -> 0 | G41: ='FS & Trend Analysis'!G45/'FS & Trend Analysis'!G$62 -> 0
A42: Non-Current Liabilities | B42: ='FS & Trend Analysis'!B46/'FS & Trend Analysis'!B$62 -> 0 | C42: ='FS & Trend Analysis'!C46/'FS & Trend Analysis'!C$62 -> 0 | D42: ='FS & Trend Analysis'!D46/'FS & Trend Analysis'!D$62 -> 0 | E42: ='FS & Trend Analysis'!E46/'FS & Trend Analysis'!E$62 -> 0 | F42: ='FS & Trend Analysis'!F46/'FS & Trend Analysis'!F$62 -> 0 | G42: ='FS & Trend Analysis'!G46/'FS & Trend Analysis'!G$62 -> 0
A43: Borrowings | B43: ='FS & Trend Analysis'!B47/'FS & Trend Analysis'!B$62 -> 0 | C43: ='FS & Trend Analysis'!C47/'FS & Trend Analysis'!C$62 -> 0 | D43: ='FS & Trend Analysis'!D47/'FS & Trend Analysis'!D$62 -> 0 | E43: ='FS & Trend Analysis'!E47/'FS & Trend Analysis'!E$62 -> 3.1343377e-05 | F43: ='FS & Trend Analysis'!F47/'FS & Trend Analysis'!F$62 -> 0.0001031767 | G43: ='FS & Trend Analysis'!G47/'FS & Trend Analysis'!G$62 -> 0
A44: Lease liabilities | B44: ='FS & Trend Analysis'!B48/'FS & Trend Analysis'!B$62 -> 0.022143681 | C44: ='FS & Trend Analysis'!C48/'FS & Trend Analysis'!C$62 -> 0.026261991 | D44: ='FS & Trend Analysis'!D48/'FS & Trend Analysis'!D$62 -> 0.012752727 | E44: ='FS & Trend Analysis'!E48/'FS & Trend Analysis'!E$62 -> 0.0083582339 | F44: ='FS & Trend Analysis'!F48/'FS & Trend Analysis'!F$62 -> 0.015373328 | G44: ='FS & Trend Analysis'!G48/'FS & Trend Analysis'!G$62 -> 0.011361961
A45: Provisions | B45: ='FS & Trend Analysis'!B49/'FS & Trend Analysis'!B$62 -> 0.002813041 | C45: ='FS & Trend Analysis'!C49/'FS & Trend Analysis'!C$62 -> 0.0012580594 | D45: ='FS & Trend Analysis'!D49/'FS & Trend Analysis'!D$62 -> 0.001396284 | E45: ='FS & Trend Analysis'!E49/'FS & Trend Analysis'!E$62 -> 0.0012850785 | F45: ='FS & Trend Analysis'!F49/'FS & Trend Analysis'!F$62 -> 0.0017081475 | G45: ='FS & Trend Analysis'!G49/'FS & Trend Analysis'!G$62 -> 0.00092124011
A46: Total Non-Current Liabilities | B46: ='FS & Trend Analysis'!B50/'FS & Trend Analysis'!B$62 -> 0.024956722 | C46: ='FS & Trend Analysis'!C50/'FS & Trend Analysis'!C$62 -> 0.02752005 | D46: ='FS & Trend Analysis'!D50/'FS & Trend Analysis'!D$62 -> 0.014149011 | E46: ='FS & Trend Analysis'!E50/'FS & Trend Analysis'!E$62 -> 0.0096746557 | F46: ='FS & Trend Analysis'!F50/'FS & Trend Analysis'!F$62 -> 0.017184652 | G46: ='FS & Trend Analysis'!G50/'FS & Trend Analysis'!G$62 -> 0.012283201
B47: ='FS & Trend Analysis'!B51/'FS & Trend Analysis'!B$62 -> 0.0070686671 | C47: ='FS & Trend Analysis'!C51/'FS & Trend Analysis'!C$62 -> 0.011479792 | D47: ='FS & Trend Analysis'!D51/'FS & Trend Analysis'!D$62 -> 0.009587817 | E47: ='FS & Trend Analysis'!E51/'FS & Trend Analysis'!E$62 -> 0.010677644 | F47: ='FS & Trend Analysis'!F51/'FS & Trend Analysis'!F$62 -> 0.014857444 | G47: ='FS & Trend Analysis'!G51/'FS & Trend Analysis'!G$62 -> 0
A48: Current Liabilities | B48: ='FS & Trend Analysis'!B52/'FS & Trend Analysis'!B$62 -> 0 | C48: ='FS & Trend Analysis'!C52/'FS & Trend Analysis'!C$62 -> 0 | D48: ='FS & Trend Analysis'!D52/'FS & Trend Analysis'!D$62 -> 0 | E48: ='FS & Trend Analysis'!E52/'FS & Trend Analysis'!E$62 -> 0 | F48: ='FS & Trend Analysis'!F52/'FS & Trend Analysis'!F$62 -> 0 | G48: ='FS & Trend Analysis'!G52/'FS & Trend Analysis'!G$62 -> 0
A49: Borrowings | B49: ='FS & Trend Analysis'!B53/'FS & Trend Analysis'!B$62 -> 0 | C49: ='FS & Trend Analysis'!C53/'FS & Trend Analysis'!C$62 -> 0 | D49: ='FS & Trend Analysis'!D53/'FS & Trend Analysis'!D$62 -> 7.4468481e-05 | E49: ='FS & Trend Analysis'!E53/'FS & Trend Analysis'!E$62 -> 8.3582339e-05 | F49: ='FS & Trend Analysis'!F53/'FS & Trend Analysis'!F$62 -> 0.039069575 | G49: ='FS & Trend Analysis'!G53/'FS & Trend Analysis'!G$62 -> 0.068245467
A50: Lease liabilities | B50: ='FS & Trend Analysis'!B54/'FS & Trend Analysis'!B$62 -> 0.0070686671 | C50: ='FS & Trend Analysis'!C54/'FS & Trend Analysis'!C$62 -> 0.011479792 | D50: ='FS & Trend Analysis'!D54/'FS & Trend Analysis'!D$62 -> 0.009587817 | E50: ='FS & Trend Analysis'!E54/'FS & Trend Analysis'!E$62 -> 0.010677644 | F50: ='FS & Trend Analysis'!F54/'FS & Trend Analysis'!F$62 -> 0.014857444 | G50: ='FS & Trend Analysis'!G54/'FS & Trend Analysis'!G$62 -> 0.0080209306
A51: Trade payables - MSME | B51: ='FS & Trend Analysis'!B55/'FS & Trend Analysis'!B$62 -> 0.010098096 | C51: ='FS & Trend Analysis'!C55/'FS & Trend Analysis'!C$62 -> 0.0058185249 | D51: ='FS & Trend Analysis'!D55/'FS & Trend Analysis'!D$62 -> 0.0064229065 | E51: ='FS & Trend Analysis'!E55/'FS & Trend Analysis'!E$62 -> 0.0052447918 | F51: ='FS & Trend Analysis'!F55/'FS & Trend Analysis'!F$62 -> 0.0090795492 | G51: ='FS & Trend Analysis'!G55/'FS & Trend Analysis'!G$62 -> 0.007861249
A52: Trade payables - other creditors | B52: ='FS & Trend Analysis'!B56/'FS & Trend Analysis'!B$62 -> 0.16135314 | C52: ='FS & Trend Analysis'!C56/'FS & Trend Analysis'!C$62 -> 0.16339047 | D52: ='FS & Trend Analysis'!D56/'FS & Trend Analysis'!D$62 -> 0.16364449 | E52: ='FS & Trend Analysis'!E56/'FS & Trend Analysis'!E$62 -> 0.17636918 | F52: ='FS & Trend Analysis'!F56/'FS & Trend Analysis'!F$62 -> 0.16608009 | G52: ='FS & Trend Analysis'!G56/'FS & Trend Analysis'!G$62 -> 0.16180661
A53: Other financial liabilities | B53: ='FS & Trend Analysis'!B57/'FS & Trend Analysis'!B$62 -> 0.01940277 | C53: ='FS & Trend Analysis'!C57/'FS & Trend Analysis'!C$62 -> 0.038056298 | D53: ='FS & Trend Analysis'!D57/'FS & Trend Analysis'!D$62 -> 0.018989463 | E53: ='FS & Trend Analysis'!E57/'FS & Trend Analysis'!E$62 -> 0.029734417 | F53: ='FS & Trend Analysis'!F57/'FS & Trend Analysis'!F$62 -> 0.022079813 | G53: ='FS & Trend Analysis'!G57/'FS & Trend Analysis'!G$62 -> 0.02359603
A54: Provisions | B54: ='FS & Trend Analysis'!B58/'FS & Trend Analysis'!B$62 -> 0.036064628 | C54: ='FS & Trend Analysis'!C58/'FS & Trend Analysis'!C$62 -> 0.029328511 | D54: ='FS & Trend Analysis'!D58/'FS & Trend Analysis'!D$62 -> 0.034162416 | E54: ='FS & Trend Analysis'!E58/'FS & Trend Analysis'!E$62 -> 0.038813549 | F54: ='FS & Trend Analysis'!F58/'FS & Trend Analysis'!F$62 -> 0.055703952 | G54: ='FS & Trend Analysis'!G58/'FS & Trend Analysis'!G$62 -> 0.066071341
A55: Current tax liabilities (net) | B55: ='FS & Trend Analysis'!B59/'FS & Trend Analysis'!B$62 -> 0.041185805 | C55: ='FS & Trend Analysis'!C59/'FS & Trend Analysis'!C$62 -> 0.02814908 | D55: ='FS & Trend Analysis'!D59/'FS & Trend Analysis'!D$62 -> 0.030159735 | E55: ='FS & Trend Analysis'!E59/'FS & Trend Analysis'!E$62 -> 0.029556805 | F55: ='FS & Trend Analysis'!F59/'FS & Trend Analysis'!F$62 -> 0.021827603 | G55: ='FS & Trend Analysis'!G59/'FS & Trend Analysis'!G$62 -> 0.039613325
A56: Other current liabilities | B56: ='FS & Trend Analysis'!B60/'FS & Trend Analysis'!B$62 -> 0.070830929 | C56: ='FS & Trend Analysis'!C60/'FS & Trend Analysis'!C$62 -> 0.076741626 | D56: ='FS & Trend Analysis'!D60/'FS & Trend Analysis'!D$62 -> 0.074654652 | E56: ='FS & Trend Analysis'!E60/'FS & Trend Analysis'!E$62 -> 0.078776355 | F56: ='FS & Trend Analysis'!F60/'FS & Trend Analysis'!F$62 -> 0.093237341 | G56: ='FS & Trend Analysis'!G60/'FS & Trend Analysis'!G$62 -> 0.10559868
A57: Total Current Liabilities | B57: ='FS & Trend Analysis'!B61/'FS & Trend Analysis'!B$62 -> 0.34600404 | C57: ='FS & Trend Analysis'!C61/'FS & Trend Analysis'!C$62 -> 0.3529643 | D57: ='FS & Trend Analysis'!D61/'FS & Trend Analysis'!D$62 -> 0.33769595 | E57: ='FS & Trend Analysis'!E61/'FS & Trend Analysis'!E$62 -> 0.36925633 | F57: ='FS & Trend Analysis'!F61/'FS & Trend Analysis'!F$62 -> 0.42193537 | G57: ='FS & Trend Analysis'!G61/'FS & Trend Analysis'!G$62 -> 0.48081364
A58: TOTAL EQUITIES & LIABILITIES | B58: ='FS & Trend Analysis'!B62/'FS & Trend Analysis'!B$62 -> 1 | C58: ='FS & Trend Analysis'!C62/'FS & Trend Analysis'!C$62 -> 1 | D58: ='FS & Trend Analysis'!D62/'FS & Trend Analysis'!D$62 -> 1 | E58: ='FS & Trend Analysis'!E62/'FS & Trend Analysis'!E$62 -> 1 | F58: ='FS & Trend Analysis'!F62/'FS & Trend Analysis'!F$62 -> 1 | G58: ='FS & Trend Analysis'!G62/'FS & Trend Analysis'!G$62 -> 1
A60: Assets
A61: Non-Current Assets
A62: Property, plant and equipment | B62: ='FS & Trend Analysis'!B65/'FS & Trend Analysis'!B$93 -> 0.059939411 | C62: ='FS & Trend Analysis'!C65/'FS & Trend Analysis'!C$93 -> 0.066834408 | D62: ='FS & Trend Analysis'!D65/'FS & Trend Analysis'!D$93 -> 0.078570099 | E62: ='FS & Trend Analysis'!E65/'FS & Trend Analysis'!E$93 -> 0.11016892 | F62: ='FS & Trend Analysis'!F65/'FS & Trend Analysis'!F$93 -> 0.13773258 | G62: ='FS & Trend Analysis'!G65/'FS & Trend Analysis'!G$93 -> 0.13570481
A63: Right-of-use assets | B63: ='FS & Trend Analysis'!B66/'FS & Trend Analysis'!B$93 -> 0.027481246 | C63: ='FS & Trend Analysis'!C66/'FS & Trend Analysis'!C$93 -> 0.035933323 | D63: ='FS & Trend Analysis'!D66/'FS & Trend Analysis'!D$93 -> 0.021132005 | E63: ='FS & Trend Analysis'!E66/'FS & Trend Analysis'!E$93 -> 0.019436937 | F63: ='FS & Trend Analysis'!F66/'FS & Trend Analysis'!F$93 -> 0.02987607 | G63: ='FS & Trend Analysis'!G66/'FS & Trend Analysis'!G$93 -> 0.020193583
A64: Capital work-in-progress | B64: ='FS & Trend Analysis'!B67/'FS & Trend Analysis'!B$93 -> 0.0050490479 | C64: ='FS & Trend Analysis'!C67/'FS & Trend Analysis'!C$93 -> 0.0056612675 | D64: ='FS & Trend Analysis'!D67/'FS & Trend Analysis'!D$93 -> 0.0034444238 | E64: ='FS & Trend Analysis'!E67/'FS & Trend Analysis'!E$93 -> 0.0075225225 | F64: ='FS & Trend Analysis'!F67/'FS & Trend Analysis'!F$93 -> 0.010054226 | G64: ='FS & Trend Analysis'!G67/'FS & Trend Analysis'!G$93 -> 0.0095931804
A65: Intangible assets | B65: ='FS & Trend Analysis'!B68/'FS & Trend Analysis'!B$93 -> 0.00079342181 | C65: ='FS & Trend Analysis'!C68/'FS & Trend Analysis'!C$93 -> 0.0018870892 | D65: ='FS & Trend Analysis'!D68/'FS & Trend Analysis'!D$93 -> 0.0032582387 | E65: ='FS & Trend Analysis'!E68/'FS & Trend Analysis'!E$93 -> 0.0035135135 | F65: ='FS & Trend Analysis'!F68/'FS & Trend Analysis'!F$93 -> 0.0028202277 | G65: ='FS & Trend Analysis'!G68/'FS & Trend Analysis'!G$93 -> 0.0038814917
A66: Intangible assets under development | B66: ='FS & Trend Analysis'!B69/'FS & Trend Analysis'!B$93 -> 0 | C66: ='FS & Trend Analysis'!C69/'FS & Trend Analysis'!C$93 -> 0 | D66: ='FS & Trend Analysis'!D69/'FS & Trend Analysis'!D$93 -> 0 | E66: ='FS & Trend Analysis'!E69/'FS & Trend Analysis'!E$93 -> 0.0018018018 | F66: ='FS & Trend Analysis'!F69/'FS & Trend Analysis'!F$93 -> 0.00091714721 | G66: ='FS & Trend Analysis'!G69/'FS & Trend Analysis'!G$93 -> 0.0010317889
A67: Investment property | B67: ='FS & Trend Analysis'!B70/'FS & Trend Analysis'!B$93 -> 0.0041834968 | C67: ='FS & Trend Analysis'!C70/'FS & Trend Analysis'!C$93 -> 0.0058971536 | D67: ='FS & Trend Analysis'!D70/'FS & Trend Analysis'!D$93 -> 0.012939862 | E67: ='FS & Trend Analysis'!E70/'FS & Trend Analysis'!E$93 -> 0.0028490991 | F67: ='FS & Trend Analysis'!F70/'FS & Trend Analysis'!F$93 -> 0 | G67: ='FS & Trend Analysis'!G70/'FS & Trend Analysis'!G$93 -> 0
A68: Financial assets | B68: ='FS & Trend Analysis'!B71/'FS & Trend Analysis'!B$93 -> 0 | C68: ='FS & Trend Analysis'!C71/'FS & Trend Analysis'!C$93 -> 0 | D68: ='FS & Trend Analysis'!D71/'FS & Trend Analysis'!D$93 -> 0 | E68: ='FS & Trend Analysis'!E71/'FS & Trend Analysis'!E$93 -> 0 | F68: ='FS & Trend Analysis'!F71/'FS & Trend Analysis'!F$93 -> 0 | G68: ='FS & Trend Analysis'!G71/'FS & Trend Analysis'!G$93 -> 0
A69: Investments in subsidiaries and associate/joint ventures | B69: ='FS & Trend Analysis'!B72/'FS & Trend Analysis'!B$93 -> 0.021710906 | C69: ='FS & Trend Analysis'!C72/'FS & Trend Analysis'!C$93 -> 0.018399119 | D69: ='FS & Trend Analysis'!D72/'FS & Trend Analysis'!D$93 -> 0.020852728 | E69: ='FS & Trend Analysis'!E72/'FS & Trend Analysis'!E$93 -> 0.023186937 | F69: ='FS & Trend Analysis'!F72/'FS & Trend Analysis'!F$93 -> 0.024866154 | G69: ='FS & Trend Analysis'!G72/'FS & Trend Analysis'!G$93 -> 0.02482435
A70: Trade receivables | B70: ='FS & Trend Analysis'!B73/'FS & Trend Analysis'!B$93 -> 0.025317369 | C70: ='FS & Trend Analysis'!C73/'FS & Trend Analysis'!C$93 -> 0.026733763 | D70: ='FS & Trend Analysis'!D73/'FS & Trend Analysis'!D$93 -> 0.033978775 | E70: ='FS & Trend Analysis'!E73/'FS & Trend Analysis'!E$93 -> 0 | F70: ='FS & Trend Analysis'!F73/'FS & Trend Analysis'!F$93 -> 0 | G70: ='FS & Trend Analysis'!G73/'FS & Trend Analysis'!G$93 -> 0
A71: Loans | B71: ='FS & Trend Analysis'!B74/'FS & Trend Analysis'!B$93 -> 0 | C71: ='FS & Trend Analysis'!C74/'FS & Trend Analysis'!C$93 -> 0 | D71: ='FS & Trend Analysis'!D74/'FS & Trend Analysis'!D$93 -> 0 | E71: ='FS & Trend Analysis'!E74/'FS & Trend Analysis'!E$93 -> 0 | F71: ='FS & Trend Analysis'!F74/'FS & Trend Analysis'!F$93 -> 0 | G71: ='FS & Trend Analysis'!G74/'FS & Trend Analysis'!G$93 -> 0.021397337
A72: Other financial assets | B72: ='FS & Trend Analysis'!B75/'FS & Trend Analysis'!B$93 -> 0.022215811 | C72: ='FS & Trend Analysis'!C75/'FS & Trend Analysis'!C$93 -> 0.030193427 | D72: ='FS & Trend Analysis'!D75/'FS & Trend Analysis'!D$93 -> 0.010426364 | E72: ='FS & Trend Analysis'!E75/'FS & Trend Analysis'!E$93 -> 0.016463964 | F72: ='FS & Trend Analysis'!F75/'FS & Trend Analysis'!F$93 -> 0.016978688 | G72: ='FS & Trend Analysis'!G75/'FS & Trend Analysis'!G$93 -> 0.0097282956
A73: Deferred tax assets (net) | B73: ='FS & Trend Analysis'!B76/'FS & Trend Analysis'!B$93 -> 0.020484709 | C73: ='FS & Trend Analysis'!C76/'FS & Trend Analysis'!C$93 -> 0.012187451 | D73: ='FS & Trend Analysis'!D76/'FS & Trend Analysis'!D$93 -> 0.016477379 | E73: ='FS & Trend Analysis'!E76/'FS & Trend Analysis'!E$93 -> 0.017713964 | F73: ='FS & Trend Analysis'!F76/'FS & Trend Analysis'!F$93 -> 0.016371078 | G73: ='FS & Trend Analysis'!G76/'FS & Trend Analysis'!G$93 -> 0.021016558
... A76: Total Non-Current Assets | B76: ='FS & Trend Analysis'!B79/'FS & Trend Analysis'!B$93 -> 0.29284478 | C76: ='FS & Trend Analysis'!C79/'FS & Trend Analysis'!C$93 -> 0.30673062 | D76: ='FS & Trend Analysis'!D79/'FS & Trend Analysis'!D$93 -> 0.3466766 | E76: ='FS & Trend Analysis'!E79/'FS & Trend Analysis'!E$93 -> 0.37727477 | F76: ='FS & Trend Analysis'!F79/'FS & Trend Analysis'!F$93 -> 0.40503514 | G76: ='FS & Trend Analysis'!G79/'FS & Trend Analysis'!G$93 -> 0.41050459
B77: ='FS & Trend Analysis'!B80/'FS & Trend Analysis'!B$93 -> 0 | C77: ='FS & Trend Analysis'!C80/'FS & Trend Analysis'!C$93 -> 0 | D77: ='FS & Trend Analysis'!D80/'FS & Trend Analysis'!D$93 -> 0 | E77: ='FS & Trend Analysis'!E80/'FS & Trend Analysis'!E$93 -> 0 | F77: ='FS & Trend Analysis'!F80/'FS & Trend Analysis'!F$93 -> 0 | G77: ='FS & Trend Analysis'!G80/'FS & Trend Analysis'!G$93 -> 0
A78: Current Assets | B78: ='FS & Trend Analysis'!B81/'FS & Trend Analysis'!B$93 -> 0 | C78: ='FS & Trend Analysis'!C81/'FS & Trend Analysis'!C$93 -> 0 | D78: ='FS & Trend Analysis'!D81/'FS & Trend Analysis'!D$93 -> 0 | E78: ='FS & Trend Analysis'!E81/'FS & Trend Analysis'!E$93 -> 0 | F78: ='FS & Trend Analysis'!F81/'FS & Trend Analysis'!F$93 -> 0 | G78: ='FS & Trend Analysis'!G81/'FS & Trend Analysis'!G$93 -> 0
A79: Inventories | B79: ='FS & Trend Analysis'!B82/'FS & Trend Analysis'!B$93 -> 0.19179169 | C79: ='FS & Trend Analysis'!C82/'FS & Trend Analysis'!C$93 -> 0.18123919 | D79: ='FS & Trend Analysis'!D82/'FS & Trend Analysis'!D$93 -> 0.1920499 | E79: ='FS & Trend Analysis'!E82/'FS & Trend Analysis'!E$93 -> 0.25112613 | F79: ='FS & Trend Analysis'!F82/'FS & Trend Analysis'!F$93 -> 0.24812271 | G79: ='FS & Trend Analysis'!G82/'FS & Trend Analysis'!G$93 -> 0.24333022
A80: Financial assets | B80: ='FS & Trend Analysis'!B83/'FS & Trend Analysis'!B$93 -> 0 | C80: ='FS & Trend Analysis'!C83/'FS & Trend Analysis'!C$93 -> 0 | D80: ='FS & Trend Analysis'!D83/'FS & Trend Analysis'!D$93 -> 0 | E80: ='FS & Trend Analysis'!E83/'FS & Trend Analysis'!E$93 -> 0 | F80: ='FS & Trend Analysis'!F83/'FS & Trend Analysis'!F$93 -> 0 | G80: ='FS & Trend Analysis'!G83/'FS & Trend Analysis'!G$93 -> 0
A81: Investments | B81: ='FS & Trend Analysis'!B84/'FS & Trend Analysis'!B$93 -> 0.083165032 | C81: ='FS & Trend Analysis'!C84/'FS & Trend Analysis'!C$93 -> 0.068642868 | D81: ='FS & Trend Analysis'!D84/'FS & Trend Analysis'!D$93 -> 0.055762428 | E81: ='FS & Trend Analysis'!E84/'FS & Trend Analysis'!E$93 -> 0.028806306 | F81: ='FS & Trend Analysis'!F84/'FS & Trend Analysis'!F$93 -> 0.0254623 | G81: ='FS & Trend Analysis'!G84/'FS & Trend Analysis'!G$93 -> 0
A82: Trade receivables | B82: ='FS & Trend Analysis'!B85/'FS & Trend Analysis'!B$93 -> 0.25908829 | C82: ='FS & Trend Analysis'!C85/'FS & Trend Analysis'!C$93 -> 0.25853122 | D82: ='FS & Trend Analysis'!D85/'FS & Trend Analysis'!D$93 -> 0.25721467 | E82: ='FS & Trend Analysis'!E85/'FS & Trend Analysis'!E$93 -> 0.26833333 | F82: ='FS & Trend Analysis'!F85/'FS & Trend Analysis'!F$93 -> 0.26392058 | G82: ='FS & Trend Analysis'!G85/'FS & Trend Analysis'!G$93 -> 0.26532944
A83: Cash and cash equivalents | B83: ='FS & Trend Analysis'!B86/'FS & Trend Analysis'!B$93 -> 0.061670514 | C83: ='FS & Trend Analysis'!C86/'FS & Trend Analysis'!C$93 -> 0.090423022 | D83: ='FS & Trend Analysis'!D86/'FS & Trend Analysis'!D$93 -> 0.095047477 | E83: ='FS & Trend Analysis'!E86/'FS & Trend Analysis'!E$93 -> 0.0091666667 | F83: ='FS & Trend Analysis'!F86/'FS & Trend Analysis'!F$93 -> 0.0030953718 | G83: ='FS & Trend Analysis'!G86/'FS & Trend Analysis'!G$93 -> 0.0060433351
A84: Bank balances other than cash and cash equivalents | B84: ='FS & Trend Analysis'!B87/'FS & Trend Analysis'!B$93 -> 0.074076746 | C84: ='FS & Trend Analysis'!C87/'FS & Trend Analysis'!C$93 -> 0.04898569 | D84: ='FS & Trend Analysis'!D87/'FS & Trend Analysis'!D$93 -> 0.017501396 | E84: ='FS & Trend Analysis'!E87/'FS & Trend Analysis'!E$93 -> 0.0086486486 | F84: ='FS & Trend Analysis'!F87/'FS & Trend Analysis'!F$93 -> 0.00066493173 | G84: ='FS & Trend Analysis'!G87/'FS & Trend Analysis'!G$93 -> 0.00074927529
A85: Loans | B85: ='FS & Trend Analysis'!B88/'FS & Trend Analysis'!B$93 -> 7.2129256e-05 | C85: ='FS & Trend Analysis'!C88/'FS & Trend Analysis'!C$93 -> 0.0017298317 | D85: ='FS & Trend Analysis'!D88/'FS & Trend Analysis'!D$93 -> 0.00093092534 | E85: ='FS & Trend Analysis'!E88/'FS & Trend Analysis'!E$93 -> 0.012240991 | F85: ='FS & Trend Analysis'!F88/'FS & Trend Analysis'!F$93 -> 0.015912504 | G85: ='FS & Trend Analysis'!G88/'FS & Trend Analysis'!G$93 -> 0.012344618
A86: Other financial assets | B86: ='FS & Trend Analysis'!B89/'FS & Trend Analysis'!B$93 -> 0.0042556261 | C86: ='FS & Trend Analysis'!C89/'FS & Trend Analysis'!C$93 -> 0.020364837 | D86: ='FS & Trend Analysis'!D89/'FS & Trend Analysis'!D$93 -> 0.0037237014 | E86: ='FS & Trend Analysis'!E89/'FS & Trend Analysis'!E$93 -> 0.015371622 | F86: ='FS & Trend Analysis'!F89/'FS & Trend Analysis'!F$93 -> 0.0092402582 | G86: ='FS & Trend Analysis'!G89/'FS & Trend Analysis'!G$93 -> 0.025143713
A87: Other current assets | B87: ='FS & Trend Analysis'!B90/'FS & Trend Analysis'!B$93 -> 0.028202539 | C87: ='FS & Trend Analysis'!C90/'FS & Trend Analysis'!C$93 -> 0.023352728 | D87: ='FS & Trend Analysis'!D90/'FS & Trend Analysis'!D$93 -> 0.031092906 | E87: ='FS & Trend Analysis'!E90/'FS & Trend Analysis'!E$93 -> 0.029031532 | F87: ='FS & Trend Analysis'!F90/'FS & Trend Analysis'!F$93 -> 0.028546207 | G87: ='FS & Trend Analysis'!G90/'FS & Trend Analysis'!G$93 -> 0.036554808
A88: Assets classified as held for sale | B88: ='FS & Trend Analysis'!B91/'FS & Trend Analysis'!B$93 -> 0.0048326601 | C88: ='FS & Trend Analysis'!C91/'FS & Trend Analysis'!C$93 -> 0 | D88: ='FS & Trend Analysis'!D91/'FS & Trend Analysis'!D$93 -> 0 | E88: ='FS & Trend Analysis'!E91/'FS & Trend Analysis'!E$93 -> 0 | F88: ='FS & Trend Analysis'!F91/'FS & Trend Analysis'!F$93 -> 0 | G88: ='FS & Trend Analysis'!G91/'FS & Trend Analysis'!G$93 -> 0
A89: Total Current Assets | B89: ='FS & Trend Analysis'!B92/'FS & Trend Analysis'!B$93 -> 0.70715522 | C89: ='FS & Trend Analysis'!C92/'FS & Trend Analysis'!C$93 -> 0.69326938 | D89: ='FS & Trend Analysis'!D92/'FS & Trend Analysis'!D$93 -> 0.6533234 | E89: ='FS & Trend Analysis'!E92/'FS & Trend Analysis'!E$93 -> 0.62272523 | F89: ='FS & Trend Analysis'!F92/'FS & Trend Analysis'!F$93 -> 0.59496486 | G89: ='FS & Trend Analysis'!G92/'FS & Trend Analysis'!G$93 -> 0.58949541
A90: TOTAL ASSETS | B90: ='FS & Trend Analysis'!B93/'FS & Trend Analysis'!B$93 -> 1 | C90: ='FS & Trend Analysis'!C93/'FS & Trend Analysis'!C$93 -> 1 | D90: ='FS & Trend Analysis'!D93/'FS & Trend Analysis'!D$93 -> 1 | E90: ='FS & Trend Analysis'!E93/'FS & Trend Analysis'!E$93 -> 1 | F90: ='FS & Trend Analysis'!F93/'FS & Trend Analysis'!F$93 -> 1 | G90: ='FS & Trend Analysis'!G93/'FS & Trend Analysis'!G$93 -> 1

Sheet Comparative FS
B2: Comparative Financial Statements (YoY)
B4: Comparative Income Statement
B5: Particulars | C5: 46112 | D5: 45747 | E5: 45382 | F5: 45016 | G5: 44651
B6: Revenue from Operations | C6: =('FS & Trend Analysis'!B6-'FS & Trend Analysis'!C6)/'FS & Trend Analysis'!C6 -> 0.037378641 | D6: =('FS & Trend Analysis'!C6-'FS & Trend Analysis'!D6)/'FS & Trend Analysis'!D6 -> 0.054787506 | E6: =('FS & Trend Analysis'!D6-'FS & Trend Analysis'!E6)/'FS & Trend Analysis'!E6 -> -0.079374864 | F6: =('FS & Trend Analysis'!E6-'FS & Trend Analysis'!F6)/'FS & Trend Analysis'!F6 -> -0.10382478 | G6: =('FS & Trend Analysis'!F6-'FS & Trend Analysis'!G6)/'FS & Trend Analysis'!G6 -> 0.13234277
B7: Other Income | C7: =('FS & Trend Analysis'!B7-'FS & Trend Analysis'!C7)/'FS & Trend Analysis'!C7 -> 0.35211268 | D7: =('FS & Trend Analysis'!C7-'FS & Trend Analysis'!D7)/'FS & Trend Analysis'!D7 -> 0.27164179 | E7: =('FS & Trend Analysis'!D7-'FS & Trend Analysis'!E7)/'FS & Trend Analysis'!E7 -> 3.527027 | F7: =('FS & Trend Analysis'!E7-'FS & Trend Analysis'!F7)/'FS & Trend Analysis'!F7 -> 1.1764706 | G7: =('FS & Trend Analysis'!F7-'FS & Trend Analysis'!G7)/'FS & Trend Analysis'!G7 -> -0.28870293
B8: Total Income | C8: =('FS & Trend Analysis'!B8-'FS & Trend Analysis'!C8)/'FS & Trend Analysis'!C8 -> 0.042306844 | D8: =('FS & Trend Analysis'!C8-'FS & Trend Analysis'!D8)/'FS & Trend Analysis'!D8 -> 0.057611569 | E8: =('FS & Trend Analysis'!D8-'FS & Trend Analysis'!E8)/'FS & Trend Analysis'!E8 -> -0.069723709 | F8: =('FS & Trend Analysis'!E8-'FS & Trend Analysis'!F8)/'FS & Trend Analysis'!F8 -> -0.10241179 | G8: =('FS & Trend Analysis'!F8-'FS & Trend Analysis'!G8)/'FS & Trend Analysis'!G8 -> 0.1316035
B10: Expenses
B11: Cost of materials consumed | C11: =('FS & Trend Analysis'!B11-'FS & Trend Analysis'!C11)/'FS & Trend Analysis'!C11 -> 0.10196583 | D11: =('FS & Trend Analysis'!C11-'FS & Trend Analysis'!D11)/'FS & Trend Analysis'!D11 -> 0.035972592 | E11: =('FS & Trend Analysis'!D11-'FS & Trend Analysis'!E11)/'FS & Trend Analysis'!E11 -> -0.015551808 | F11: =('FS & Trend Analysis'!E11-'FS & Trend Analysis'!F11)/'FS & Trend Analysis'!F11 -> 0.1144289 | G11: =('FS & Trend Analysis'!F11-'FS & Trend Analysis'!G11)/'FS & Trend Analysis'!G11 -> 0.20067191
B12: Purchase of stock-in-trade | C12: =('FS & Trend Analysis'!B12-'FS & Trend Analysis'!C12)/'FS & Trend Analysis'!C12 -> -0.064814815 | D12: =('FS & Trend Analysis'!C12-'FS & Trend Analysis'!D12)/'FS & Trend Analysis'!D12 -> 0.28 | E12: =('FS & Trend Analysis'!D12-'FS & Trend Analysis'!E12)/'FS & Trend Analysis'!E12 -> -0.21875 | F12: =('FS & Trend Analysis'!E12-'FS & Trend Analysis'!F12)/'FS & Trend Analysis'!F12 -> 0.49740035 | G12: =('FS & Trend Analysis'!F12-'FS & Trend Analysis'!G12)/'FS & Trend Analysis'!G12 -> 0.6514024
B13: Change in inventories of finished goods, work-in-progress and stock-in-trade | C13: =('FS & Trend Analysis'!B13-'FS & Trend Analysis'!C13)/'FS & Trend Analysis'!C13 -> -2.5555556 | D13: =('FS & Trend Analysis'!C13-'FS & Trend Analysis'!D13)/'FS & Trend Analysis'!D13 -> -0.24369748 | E13: =('FS & Trend Analysis'!D13-'FS & Trend Analysis'!E13)/'FS & Trend Analysis'!E13 -> -1.9224806 | F13: =('FS & Trend Analysis'!E13-'FS & Trend Analysis'!F13)/'FS & Trend Analysis'!F13 -> 0.55797101 | G13: =('FS & Trend Analysis'!F13-'FS & Trend Analysis'!G13)/'FS & Trend Analysis'!G13 -> -1.6359447
B14: Excise duty | C14: =('FS & Trend Analysis'!B14-'FS & Trend Analysis'!C14)/'FS & Trend Analysis'!C14 -> 0.0082856579 | D14: =('FS & Trend Analysis'!C14-'FS & Trend Analysis'!D14)/'FS & Trend Analysis'!D14 -> 0.034700959 | E14: =('FS & Trend Analysis'!D14-'FS & Trend Analysis'!E14)/'FS & Trend Analysis'!E14 -> -0.14572193 | F14: =('FS & Trend Analysis'!E14-'FS & Trend Analysis'!F14)/'FS & Trend Analysis'!F14 -> -0.19415429 | G14: =('FS & Trend Analysis'!F14-'FS & Trend Analysis'!G14)/'FS & Trend Analysis'!G14 -> 0.10689991
B15: Employee benefits expense | C15: =('FS & Trend Analysis'!B15-'FS & Trend Analysis'!C15)/'FS & Trend Analysis'!C15 -> 0.029752066 | D15: =('FS & Trend Analysis'!C15-'FS & Trend Analysis'!D15)/'FS & Trend Analysis'!D15 -> 0.11418048 | E15: =('FS & Trend Analysis'!D15-'FS & Trend Analysis'!E15)/'FS & Trend Analysis'!E15 -> -0.10543657 | F15: =('FS & Trend Analysis'!E15-'FS & Trend Analysis'!F15)/'FS & Trend Analysis'!F15 -> -0.066153846 | G15: =('FS & Trend Analysis'!F15-'FS & Trend Analysis'!G15)/'FS & Trend Analysis'!G15 -> 0.20281273
B16: Advertisement and sales promotion | C16: =('FS & Trend Analysis'!B16-'FS & Trend Analysis'!C16)/'FS & Trend Analysis'!C16 -> 0.14804965 | D16: =('FS & Trend Analysis'!C16-'FS & Trend Analysis'!D16)/'FS & Trend Analysis'!D16 -> 0.083573487 | E16: =('FS & Trend Analysis'!D16-'FS & Trend Analysis'!E16)/'FS & Trend Analysis'!E16 -> 0.13152174 | F16: =('FS & Trend Analysis'!E16-'FS & Trend Analysis'!F16)/'FS & Trend Analysis'!F16 -> 0.33526851 | G16: =('FS & Trend Analysis'!F16-'FS & Trend Analysis'!G16)/'FS & Trend Analysis'!G16 -> 0.20538838
B17: Other expenses | C17: =('FS & Trend Analysis'!B17-'FS & Trend Analysis'!C17)/'FS & Trend Analysis'!C17 -> 0.13212996 | D17: =('FS & Trend Analysis'!C17-'FS & Trend Analysis'!D17)/'FS & Trend Analysis'!D17 -> 0.024408284 | E17: =('FS & Trend Analysis'!D17-'FS & Trend Analysis'!E17)/'FS & Trend Analysis'!E17 -> -0.0029498525 | F17: =('FS & Trend Analysis'!E17-'FS & Trend Analysis'!F17)/'FS & Trend Analysis'!F17 -> 0.040675365 | G17: =('FS & Trend Analysis'!F17-'FS & Trend Analysis'!G17)/'FS & Trend Analysis'!G17 -> 0.023646791
B18: Total expenses | C18: =('FS & Trend Analysis'!B18-'FS & Trend Analysis'!C18)/'FS & Trend Analysis'!C18 -> 0.030863199 | D18: =('FS & Trend Analysis'!C18-'FS & Trend Analysis'!D18)/'FS & Trend Analysis'!D18 -> 0.043959292 | E18: =('FS & Trend Analysis'!D18-'FS & Trend Analysis'!E18)/'FS & Trend Analysis'!E18 -> -0.094728392 | F18: =('FS & Trend Analysis'!E18-'FS & Trend Analysis'!F18)/'FS & Trend Analysis'!F18 -> -0.10641452 | G18: =('FS & Trend Analysis'!F18-'FS & Trend Analysis'!G18)/'FS & Trend Analysis'!G18 -> 0.11988768
B20: EBITDA | C20: =('FS & Trend Analysis'!B20-'FS & Trend Analysis'!C20)/'FS & Trend Analysis'!C20 -> 0.15619968 | D20: =('FS & Trend Analysis'!C20-'FS & Trend Analysis'!D20)/'FS & Trend Analysis'!D20 -> 0.21585903 | E20: =('FS & Trend Analysis'!D20-'FS & Trend Analysis'!E20)/'FS & Trend Analysis'!E20 -> 0.3683858 | F20: =('FS & Trend Analysis'!E20-'FS & Trend Analysis'!F20)/'FS & Trend Analysis'!F20 -> -0.025965553 | G20: =('FS & Trend Analysis'!F20-'FS & Trend Analysis'!G20)/'FS & Trend Analysis'!G20 -> 0.4141526
B21: Depreciation and amortisation expense | C21: =('FS & Trend Analysis'!B21-'FS & Trend Analysis'!C21)/'FS & Trend Analysis'!C21 -> 0.032846715 | D21: =('FS & Trend Analysis'!C21-'FS & Trend Analysis'!D21)/'FS & Trend Analysis'!D21 -> 0.037878788 | E21: =('FS & Trend Analysis'!D21-'FS & Trend Analysis'!E21)/'FS & Trend Analysis'!E21 -> -0.025830258 | F21: =('FS & Trend Analysis'!E21-'FS & Trend Analysis'!F21)/'FS & Trend Analysis'!F21 -> -0.062283737 | G21: =('FS & Trend Analysis'!F21-'FS & Trend Analysis'!G21)/'FS & Trend Analysis'!G21 -> 0.15924589
B22: EBIT | C22: =('FS & Trend Analysis'!B22-'FS & Trend Analysis'!C22)/'FS & Trend Analysis'!C22 -> 0.17149321 | D22: =('FS & Trend Analysis'!C22-'FS & Trend Analysis'!D22)/'FS & Trend Analysis'!D22 -> 0.24227094 | E22: =('FS & Trend Analysis'!D22-'FS & Trend Analysis'!E22)/'FS & Trend Analysis'!E22 -> 0.45581015 | F22: =('FS & Trend Analysis'!E22-'FS & Trend Analysis'!F22)/'FS & Trend Analysis'!F22 -> -0.017526934 | G22: =('FS & Trend Analysis'!F22-'FS & Trend Analysis'!G22)/'FS & Trend Analysis'!G22 -> 0.49029475
B23: Finance costs | C23: =('FS & Trend Analysis'!B23-'FS & Trend Analysis'!C23)/'FS & Trend Analysis'!C23 -> 0.7752809 | D23: =('FS & Trend Analysis'!C23-'FS & Trend Analysis'!D23)/'FS & Trend Analysis'!D23 -> 0.17105263 | E23: =('FS & Trend Analysis'!D23-'FS & Trend Analysis'!E23)/'FS & Trend Analysis'!E23 -> -0.26923077 | F23: =('FS & Trend Analysis'!E23-'FS & Trend Analysis'!F23)/'FS & Trend Analysis'!F23 -> 0.18181818 | G23: =('FS & Trend Analysis'!F23-'FS & Trend Analysis'!G23)/'FS & Trend Analysis'!G23 -> -0.46924005
B24: PBT before profits of JVs | C24: =('FS & Trend Analysis'!B24-'FS & Trend Analysis'!C24)/'FS & Trend Analysis'!C24 -> 0.14615747 | D24: =('FS & Trend Analysis'!C24-'FS & Trend Analysis'!D24)/'FS & Trend Analysis'!D24 -> 0.24544921 | E24: =('FS & Trend Analysis'!D24-'FS & Trend Analysis'!E24)/'FS & Trend Analysis'!E24 -> 0.52325581 | F24: =('FS & Trend Analysis'!E24-'FS & Trend Analysis'!F24)/'FS & Trend Analysis'!F24 -> -0.03270462 | G24: =('FS & Trend Analysis'!F24-'FS & Trend Analysis'!G24)/'FS & Trend Analysis'!G24 -> 0.72816986
B25: Add: Share of Profits of JVs
B26: PBT & Exceptional Items | C26: =('FS & Trend Analysis'!B26-'FS & Trend Analysis'!C26)/'FS & Trend Analysis'!C26 -> 0.14615747 | D26: =('FS & Trend Analysis'!C26-'FS & Trend Analysis'!D26)/'FS & Trend Analysis'!D26 -> 0.24544921 | E26: =('FS & Trend Analysis'!D26-'FS & Trend Analysis'!E26)/'FS & Trend Analysis'!E26 -> 0.52325581 | F26: =('FS & Trend Analysis'!E26-'FS & Trend Analysis'!F26)/'FS & Trend Analysis'!F26 -> -0.03270462 | G26: =('FS & Trend Analysis'!F26-'FS & Trend Analysis'!G26)/'FS & Trend Analysis'!G26 -> 0.72816986
B27: Exceptional Items | C27: =('FS & Trend Analysis'!B27-'FS & Trend Analysis'!C27)/'FS & Trend Analysis'!C27 -> 0.4 | D27: =('FS & Trend Analysis'!C27-'FS & Trend Analysis'!D27)/'FS & Trend Analysis'!D27 -> 2.8235294 | E27: =('FS & Trend Analysis'!D27-'FS & Trend Analysis'!E27)/'FS & Trend Analysis'!E27 -> -1.0994152 | F27: =('FS & Trend Analysis'!E27-'FS & Trend Analysis'!F27)/'FS & Trend Analysis'!F27 -> -2.0961538 | G27: =('FS & Trend Analysis'!F27-'FS & Trend Analysis'!G27)/'FS & Trend Analysis'!G27 -> 0.030383091
B28: PBT | C28: =('FS & Trend Analysis'!B28-'FS & Trend Analysis'!C28)/'FS & Trend Analysis'!C28 -> 0.1381323 | D28: =('FS & Trend Analysis'!C28-'FS & Trend Analysis'!D28)/'FS & Trend Analysis'!D28 -> 0.21945433 | E28: =('FS & Trend Analysis'!D28-'FS & Trend Analysis'!E28)/'FS & Trend Analysis'!E28 -> 0.30799069 | F28: =('FS & Trend Analysis'!E28-'FS & Trend Analysis'!F28)/'FS & Trend Analysis'!F28 -> 0.28925785 | G28: =('FS & Trend Analysis'!F28-'FS & Trend Analysis'!G28)/'FS & Trend Analysis'!G28 -> 0.93235408
B29: Tax | C29: =('FS & Trend Analysis'!B29-'FS & Trend Analysis'!C29)/'FS & Trend Analysis'!C29 -> 0.024096386 | D29: =('FS & Trend Analysis'!C29-'FS & Trend Analysis'!D29)/'FS & Trend Analysis'!D29 -> 0.3315508 | E29: =('FS & Trend Analysis'!D29-'FS & Trend Analysis'!E29)/'FS & Trend Analysis'!E29 -> 0.57805907 | F29: =('FS & Trend Analysis'!E29-'FS & Trend Analysis'!F29)/'FS & Trend Analysis'!F29 -> 0.48125 | G29: =('FS & Trend Analysis'!F29-'FS & Trend Analysis'!G29)/'FS & Trend Analysis'!G29 -> 0.0081915564
B30: PAT | C30: =('FS & Trend Analysis'!B30-'FS & Trend Analysis'!C30)/'FS & Trend Analysis'!C30 -> 0.1745828 | D30: =('FS & Trend Analysis'!C30-'FS & Trend Analysis'!D30)/'FS & Trend Analysis'!D30 -> 0.1875 | E30: =('FS & Trend Analysis'!D30-'FS & Trend Analysis'!E30)/'FS & Trend Analysis'!E30 -> 0.24714829 | F30: =('FS & Trend Analysis'!E30-'FS & Trend Analysis'!F30)/'FS & Trend Analysis'!F30 -> 0.25267921 | G30: =('FS & Trend Analysis'!F30-'FS & Trend Analysis'!G30)/'FS & Trend Analysis'!G30 -> 1.3412322
B31: Less: Share of Minority Interest
B32: PAT for Equity Shareholders | C32: =('FS & Trend Analysis'!B32-'FS & Trend Analysis'!C32)/'FS & Trend Analysis'!C32 -> 0.1745828 | D32: =('FS & Trend Analysis'!C32-'FS & Trend Analysis'!D32)/'FS & Trend Analysis'!D32 -> 0.1875 | E32: =('FS & Trend Analysis'!D32-'FS & Trend Analysis'!E32)/'FS & Trend Analysis'!E32 -> 0.24714829 | F32: =('FS & Trend Analysis'!E32-'FS & Trend Analysis'!F32)/'FS & Trend Analysis'!F32 -> 0.25267921 | G32: =('FS & Trend Analysis'!F32-'FS & Trend Analysis'!G32)/'FS & Trend Analysis'!G32 -> 1.3412322
B33: Dividend | C33: =('FS & Trend Analysis'!B33-'FS & Trend Analysis'!C33)/'FS & Trend Analysis'!C33 -> 2.6085714 | D33: =('FS & Trend Analysis'!C33-'FS & Trend Analysis'!D33)/'FS & Trend Analysis'!D33 -> 0.20274914 | E33: =('FS & Trend Analysis'!D33-'FS & Trend Analysis'!E33)/'FS & Trend Analysis'!E33 -> #DIV/0! | F33: =('FS & Trend Analysis'!E33-'FS & Trend Analysis'!F33)/'FS & Trend Analysis'!F33 -> #DIV/0! | G33: =('FS & Trend Analysis'!F33-'FS & Trend Analysis'!G33)/'FS & Trend Analysis'!G33 -> #DIV/0!
B34: Tax Rate (%) | C34: =('FS & Trend Analysis'!B34-'FS & Trend Analysis'!C34)/'FS & Trend Analysis'!C34 -> -0.10019565 | D34: =('FS & Trend Analysis'!C34-'FS & Trend Analysis'!D34)/'FS & Trend Analysis'!D34 -> 0.091923469 | E34: =('FS & Trend Analysis'!D34-'FS & Trend Analysis'!E34)/'FS & Trend Analysis'!E34 -> 0.20647577 | F34: =('FS & Trend Analysis'!E34-'FS & Trend Analysis'!F34)/'FS & Trend Analysis'!F34 -> 0.1489168 | G34: =('FS & Trend Analysis'!F34-'FS & Trend Analysis'!G34)/'FS & Trend Analysis'!G34 -> -0.47825734
B39: Comparative Balance Sheet
B40: Particulars | C40: 46112 | D40: 45747 | E40: 45382 | F40: 45016 | G40: 44651
B41: Equity & Liabilities
B42: Share capital | C42: =('FS & Trend Analysis'!B40-'FS & Trend Analysis'!C40)/'FS & Trend Analysis'!C40 -> 0 | D42: =('FS & Trend Analysis'!C40-'FS & Trend Analysis'!D40)/'FS & Trend Analysis'!D40 -> 0 | E42: =('FS & Trend Analysis'!D40-'FS & Trend Analysis'!E40)/'FS & Trend Analysis'!E40 -> -0.0034364261 | F42: =('FS & Trend Analysis'!E40-'FS & Trend Analysis'!F40)/'FS & Trend Analysis'!F40 -> 0 | G42: =('FS & Trend Analysis'!F40-'FS & Trend Analysis'!G40)/'FS & Trend Analysis'!G40 -> 0.0013764625
B43: Share suspense | C43: =('FS & Trend Analysis'!B41-'FS & Trend Analysis'!C41)/'FS & Trend Analysis'!C41 -> #DIV/0! | D43: =('FS & Trend Analysis'!C41-'FS & Trend Analysis'!D41)/'FS & Trend Analysis'!D41 -> #DIV/0! | E43: =('FS & Trend Analysis'!D41-'FS & Trend Analysis'!E41)/'FS & Trend Analysis'!E41 -> #DIV/0! | F43: =('FS & Trend Analysis'!E41-'FS & Trend Analysis'!F41)/'FS & Trend Analysis'!F41 -> -1 | G43: =('FS & Trend Analysis'!F41-'FS & Trend Analysis'!G41)/'FS & Trend Analysis'!G41 -> #DIV/0!
B44: Other equity | C44: =('FS & Trend Analysis'!B42-'FS & Trend Analysis'!C42)/'FS & Trend Analysis'!C42 -> #DIV/0! | D44: =('FS & Trend Analysis'!C42-'FS & Trend Analysis'!D42)/'FS & Trend Analysis'!D42 -> #DIV/0! | E44: =('FS & Trend Analysis'!D42-'FS & Trend Analysis'!E42)/'FS & Trend Analysis'!E42 -> #DIV/0! | F44: =('FS & Trend Analysis'!E42-'FS & Trend Analysis'!F42)/'FS & Trend Analysis'!F42 -> #DIV/0! | G44: =('FS & Trend Analysis'!F42-'FS & Trend Analysis'!G42)/'FS & Trend Analysis'!G42 -> #DIV/0!
B45: Reserves and surplus | C45: =('FS & Trend Analysis'!B43-'FS & Trend Analysis'!C43)/'FS & Trend Analysis'!C43 -> 0.10886993 | D45: =('FS & Trend Analysis'!C43-'FS & Trend Analysis'!D43)/'FS & Trend Analysis'!D43 -> 0.13435025 | E45: =('FS & Trend Analysis'!D43-'FS & Trend Analysis'!E43)/'FS & Trend Analysis'!E43 -> 0.17571995 | F45: =('FS & Trend Analysis'!E43-'FS & Trend Analysis'!F43)/'FS & Trend Analysis'!F43 -> 0.22166512 | G45: =('FS & Trend Analysis'!F43-'FS & Trend Analysis'!G43)/'FS & Trend Analysis'!G43 -> 0.19221399
B46: Total Equity | C46: =('FS & Trend Analysis'!B44-'FS & Trend Analysis'!C44)/'FS & Trend Analysis'!C44 -> 0.10686635 | D46: =('FS & Trend Analysis'!C44-'FS & Trend Analysis'!D44)/'FS & Trend Analysis'!D44 -> 0.13155249 | E46: =('FS & Trend Analysis'!D44-'FS & Trend Analysis'!E44)/'FS & Trend Analysis'!E44 -> 0.17133485 | F46: =('FS & Trend Analysis'!E44-'FS & Trend Analysis'!F44)/'FS & Trend Analysis'!F44 -> 0.21502299 | G46: =('FS & Trend Analysis'!F44-'FS & Trend Analysis'!G44)/'FS & Trend Analysis'!G44 -> 0.18554328
B48: Non-Current Liabilities
B49: Borrowings | C49: =('FS & Trend Analysis'!B47-'FS & Trend Analysis'!C47)/'FS & Trend Analysis'!C47 -> #DIV/0! | D49: =('FS & Trend Analysis'!C47-'FS & Trend Analysis'!D47)/'FS & Trend Analysis'!D47 -> #DIV/0! | E49: =('FS & Trend Analysis'!D47-'FS & Trend Analysis'!E47)/'FS & Trend Analysis'!E47 -> -1 | F49: =('FS & Trend Analysis'!E47-'FS & Trend Analysis'!F47)/'FS & Trend Analysis'!F47 -> -0.66666667 | G49: =('FS & Trend Analysis'!F47-'FS & Trend Analysis'!G47)/'FS & Trend Analysis'!G47 -> #DIV/0!
B50: Lease liabilities | C50: =('FS & Trend Analysis'!B48-'FS & Trend Analysis'!C48)/'FS & Trend Analysis'!C48 -> -0.080838323 | D50: =('FS & Trend Analysis'!C48-'FS & Trend Analysis'!D48)/'FS & Trend Analysis'!D48 -> 1.4379562 | E50: =('FS & Trend Analysis'!D48-'FS & Trend Analysis'!E48)/'FS & Trend Analysis'!E48 -> 0.7125 | F50: =('FS & Trend Analysis'!E48-'FS & Trend Analysis'!F48)/'FS & Trend Analysis'!F48 -> -0.40343028 | G50: =('FS & Trend Analysis'!F48-'FS & Trend Analysis'!G48)/'FS & Trend Analysis'!G48 -> 0.44972973
B51: Provisions | C51: =('FS & Trend Analysis'!B49-'FS & Trend Analysis'!C49)/'FS & Trend Analysis'!C49 -> 1.4375 | D51: =('FS & Trend Analysis'!C49-'FS & Trend Analysis'!D49)/'FS & Trend Analysis'!D49 -> 0.066666667 | E51: =('FS & Trend Analysis'!D49-'FS & Trend Analysis'!E49)/'FS & Trend Analysis'!E49 -> 0.2195122 | F51: =('FS & Trend Analysis'!E49-'FS & Trend Analysis'!F49)/'FS & Trend Analysis'!F49 -> -0.17449664 | G51: =('FS & Trend Analysis'!F49-'FS & Trend Analysis'!G49)/'FS & Trend Analysis'!G49 -> 0.98666667
B52: Total Non-Current Liabilities | C52: =('FS & Trend Analysis'!B50-'FS & Trend Analysis'!C50)/'FS & Trend Analysis'!C50 -> -0.011428571 | D52: =('FS & Trend Analysis'!C50-'FS & Trend Analysis'!D50)/'FS & Trend Analysis'!D50 -> 1.3026316 | E52: =('FS & Trend Analysis'!D50-'FS & Trend Analysis'!E50)/'FS & Trend Analysis'!E50 -> 0.64146868 | F52: =('FS & Trend Analysis'!E50-'FS & Trend Analysis'!F50)/'FS & Trend Analysis'!F50 -> -0.38225484 | G52: =('FS & Trend Analysis'!F50-'FS & Trend Analysis'!G50)/'FS & Trend Analysis'!G50 -> 0.499
C53: =('FS & Trend Analysis'!B51-'FS & Trend Analysis'!C51)/'FS & Trend Analysis'!C51 -> -0.32876712 | D53: =('FS & Trend Analysis'!C51-'FS & Trend Analysis'!D51)/'FS & Trend Analysis'!D51 -> 0.41747573 | E53: =('FS & Trend Analysis'!D51-'FS & Trend Analysis'!E51)/'FS & Trend Analysis'!E51 -> 0.0078277886 | F53: =('FS & Trend Analysis'!E51-'FS & Trend Analysis'!F51)/'FS & Trend Analysis'!F51 -> -0.21141975 | G53: =('FS & Trend Analysis'!F51-'FS & Trend Analysis'!G51)/'FS & Trend Analysis'!G51 -> #DIV/0!
B54: Current Liabilities
B55: Borrowings | C55: =('FS & Trend Analysis'!B53-'FS & Trend Analysis'!C53)/'FS & Trend Analysis'!C53 -> #DIV/0! | D55: =('FS & Trend Analysis'!C53-'FS & Trend Analysis'!D53)/'FS & Trend Analysis'!D53 -> -1 | E55: =('FS & Trend Analysis'!D53-'FS & Trend Analysis'!E53)/'FS & Trend Analysis'!E53 -> 0 | F55: =('FS & Trend Analysis'!E53-'FS & Trend Analysis'!F53)/'FS & Trend Analysis'!F53 -> -0.99765258 | G55: =('FS & Trend Analysis'!F53-'FS & Trend Analysis'!G53)/'FS & Trend Analysis'!G53 -> -0.38660907
B56: Lease liabilities | C56: =('FS & Trend Analysis'!B54-'FS & Trend Analysis'!C54)/'FS & Trend Analysis'!C54 -> -0.32876712 | D56: =('FS & Trend Analysis'!C54-'FS & Trend Analysis'!D54)/'FS & Trend Analysis'!D54 -> 0.41747573 | E56: =('FS & Trend Analysis'!D54-'FS & Trend Analysis'!E54)/'FS & Trend Analysis'!E54 -> 0.0078277886 | F56: =('FS & Trend Analysis'!E54-'FS & Trend Analysis'!F54)/'FS & Trend Analysis'!F54 -> -0.21141975 | G56: =('FS & Trend Analysis'!F54-'FS & Trend Analysis'!G54)/'FS & Trend Analysis'!G54 -> 0.98468606
B57: Trade payables - MSME | C57: =('FS & Trend Analysis'!B55-'FS & Trend Analysis'!C55)/'FS & Trend Analysis'!C55 -> 0.89189189 | D57: =('FS & Trend Analysis'!C55-'FS & Trend Analysis'!D55)/'FS & Trend Analysis'!D55 -> 0.072463768 | E57: =('FS & Trend Analysis'!D55-'FS & Trend Analysis'!E55)/'FS & Trend Analysis'!E55 -> 0.37450199 | F57: =('FS & Trend Analysis'!E55-'FS & Trend Analysis'!F55)/'FS & Trend Analysis'!F55 -> -0.36616162 | G57: =('FS & Trend Analysis'!F55-'FS & Trend Analysis'!G55)/'FS & Trend Analysis'!G55 -> 0.2375
B58: Trade payables - other creditors | C58: =('FS & Trend Analysis'!B56-'FS & Trend Analysis'!C56)/'FS & Trend Analysis'!C56 -> 0.076515881 | D58: =('FS & Trend Analysis'!C56-'FS & Trend Analysis'!D56)/'FS & Trend Analysis'!D56 -> 0.18202503 | E58: =('FS & Trend Analysis'!D56-'FS & Trend Analysis'!E56)/'FS & Trend Analysis'!E56 -> 0.0414075 | F58: =('FS & Trend Analysis'!E56-'FS & Trend Analysis'!F56)/'FS & Trend Analysis'!F56 -> 0.1652516 | G58: =('FS & Trend Analysis'!F56-'FS & Trend Analysis'!G56)/'FS & Trend Analysis'!G56 -> 0.099749488
B59: Other financial liabilities | C59: =('FS & Trend Analysis'!B57-'FS & Trend Analysis'!C57)/'FS & Trend Analysis'!C57 -> -0.44421488 | D59: =('FS & Trend Analysis'!C57-'FS & Trend Analysis'!D57)/'FS & Trend Analysis'!D57 -> 1.372549 | E59: =('FS & Trend Analysis'!D57-'FS & Trend Analysis'!E57)/'FS & Trend Analysis'!E57 -> -0.2832045 | F59: =('FS & Trend Analysis'!E57-'FS & Trend Analysis'!F57)/'FS & Trend Analysis'!F57 -> 0.47767394 | G59: =('FS & Trend Analysis'!F57-'FS & Trend Analysis'!G57)/'FS & Trend Analysis'!G57 -> 0.002602811
B60: Provisions | C60: =('FS & Trend Analysis'!B58-'FS & Trend Analysis'!C58)/'FS & Trend Analysis'!C58 -> 0.34048257 | D60: =('FS & Trend Analysis'!C58-'FS & Trend Analysis'!D58)/'FS & Trend Analysis'!D58 -> 0.016348774 | E60: =('FS & Trend Analysis'!D58-'FS & Trend Analysis'!E58)/'FS & Trend Analysis'!E58 -> -0.012113055 | F60: =('FS & Trend Analysis'!E58-'FS & Trend Analysis'!F58)/'FS & Trend Analysis'!F58 -> -0.23543939 | G60: =('FS & Trend Analysis'!F58-'FS & Trend Analysis'!G58)/'FS & Trend Analysis'!G58 -> -0.096672244
B61: Current tax liabilities (net) | C61: =('FS & Trend Analysis'!B59-'FS & Trend Analysis'!C59)/'FS & Trend Analysis'!C59 -> 0.59497207 | D61: =('FS & Trend Analysis'!C59-'FS & Trend Analysis'!D59)/'FS & Trend Analysis'!D59 -> 0.10493827 | E61: =('FS & Trend Analysis'!D59-'FS & Trend Analysis'!E59)/'FS & Trend Analysis'!E59 -> 0.14528102 | F61: =('FS & Trend Analysis'!E59-'FS & Trend Analysis'!F59)/'FS & Trend Analysis'!F59 -> 0.48581933 | G61: =('FS & Trend Analysis'!F59-'FS & Trend Analysis'!G59)/'FS & Trend Analysis'!G59 -> -0.4096124
B62: Other current liabilities | C62: =('FS & Trend Analysis'!B60-'FS & Trend Analysis'!C60)/'FS & Trend Analysis'!C60 -> 0.006147541 | D62: =('FS & Trend Analysis'!C60-'FS & Trend Analysis'!D60)/'FS & Trend Analysis'!D60 -> 0.21695761 | E62: =('FS & Trend Analysis'!D60-'FS & Trend Analysis'!E60)/'FS & Trend Analysis'!E60 -> 0.063660477 | F62: =('FS & Trend Analysis'!E60-'FS & Trend Analysis'!F60)/'FS & Trend Analysis'!F60 -> -0.072912824 | G62: =('FS & Trend Analysis'!F60-'FS & Trend Analysis'!G60)/'FS & Trend Analysis'!G60 -> -0.053972316
B63: Total Current Liabilities | C63: =('FS & Trend Analysis'!B61-'FS & Trend Analysis'!C61)/'FS & Trend Analysis'!C61 -> 0.068612163 | D63: =('FS & Trend Analysis'!C61-'FS & Trend Analysis'!D61)/'FS & Trend Analysis'!D61 -> 0.23738905 | E63: =('FS & Trend Analysis'!D61-'FS & Trend Analysis'!E61)/'FS & Trend Analysis'!E61 -> 0.026455026 | F63: =('FS & Trend Analysis'!E61-'FS & Trend Analysis'!F61)/'FS & Trend Analysis'!F61 -> -0.039722864 | G63: =('FS & Trend Analysis'!F61-'FS & Trend Analysis'!G61)/'FS & Trend Analysis'!G61 -> -0.05975373
B64: TOTAL EQUITIES & LIABILITIES | C64: =('FS & Trend Analysis'!B62-'FS & Trend Analysis'!C62)/'FS & Trend Analysis'!C62 -> 0.090108508 | D64: =('FS & Trend Analysis'!C62-'FS & Trend Analysis'!D62)/'FS & Trend Analysis'!D62 -> 0.18386268 | E64: =('FS & Trend Analysis'!D62-'FS & Trend Analysis'!E62)/'FS & Trend Analysis'!E62 -> 0.12238544 | F64: =('FS & Trend Analysis'!E62-'FS & Trend Analysis'!F62)/'FS & Trend Analysis'!F62 -> 0.097272696 | G64: =('FS & Trend Analysis'!F62-'FS & Trend Analysis'!G62)/'FS & Trend Analysis'!G62 -> 0.071451383
B65: Assets
B66: Non-Current Assets
B67: Property, plant and equipment | C67: =('FS & Trend Analysis'!B65-'FS & Trend Analysis'!C65)/'FS & Trend Analysis'!C65 -> -0.022352941 | D67: =('FS & Trend Analysis'!C65-'FS & Trend Analysis'!D65)/'FS & Trend Analysis'!D65 -> 0.0071090047 | E67: =('FS & Trend Analysis'!D65-'FS & Trend Analysis'!E65)/'FS & Trend Analysis'!E65 -> -0.13727895 | F67: =('FS & Trend Analysis'!E65-'FS & Trend Analysis'!F65)/'FS & Trend Analysis'!F65 -> -0.18570002 | G67: =('FS & Trend Analysis'!F65-'FS & Trend Analysis'!G65)/'FS & Trend Analysis'!G65 -> 0.08743664
B68: Right-of-use assets | C68: =('FS & Trend Analysis'!B66-'FS & Trend Analysis'!C66)/'FS & Trend Analysis'!C66 -> -0.16630197 | D68: =('FS & Trend Analysis'!C66-'FS & Trend Analysis'!D66)/'FS & Trend Analysis'!D66 -> 1.0132159 | E68: =('FS & Trend Analysis'!D66-'FS & Trend Analysis'!E66)/'FS & Trend Analysis'!E66 -> 0.31517961 | F68: =('FS & Trend Analysis'!E66-'FS & Trend Analysis'!F66)/'FS & Trend Analysis'!F66 -> -0.33768227 | G68: =('FS & Trend Analysis'!F66-'FS & Trend Analysis'!G66)/'FS & Trend Analysis'!G66 -> 0.58515815
B69: Capital work-in-progress | C69: =('FS & Trend Analysis'!B67-'FS & Trend Analysis'!C67)/'FS & Trend Analysis'!C67 -> -0.027777778 | D69: =('FS & Trend Analysis'!C67-'FS & Trend Analysis'!D67)/'FS & Trend Analysis'!D67 -> 0.94594595 | E69: =('FS & Trend Analysis'!D67-'FS & Trend Analysis'!E67)/'FS & Trend Analysis'!E67 -> -0.44610778 | F69: =('FS & Trend Analysis'!E67-'FS & Trend Analysis'!F67)/'FS & Trend Analysis'!F67 -> -0.23831243 | G69: =('FS & Trend Analysis'!F67-'FS & Trend Analysis'!G67)/'FS & Trend Analysis'!G67 -> 0.12291933
B70: Intangible assets | C70: =('FS & Trend Analysis'!B68-'FS & Trend Analysis'!C68)/'FS & Trend Analysis'!C68 -> -0.54166667 | D70: =('FS & Trend Analysis'!C68-'FS & Trend Analysis'!D68)/'FS & Trend Analysis'!D68 -> -0.31428571 | E70: =('FS & Trend Analysis'!D68-'FS & Trend Analysis'!E68)/'FS & Trend Analysis'!E68 -> 0.12179487 | F70: =('FS & Trend Analysis'!E68-'FS & Trend Analysis'!F68)/'FS & Trend Analysis'!F68 -> 0.26829268 | G70: =('FS & Trend Analysis'!F68-'FS & Trend Analysis'!G68)/'FS & Trend Analysis'!G68 -> -0.22151899
B71: Intangible assets under development | E71: =('FS & Trend Analysis'!D69-'FS & Trend Analysis'!E69)/'FS & Trend Analysis'!E69 -> -1 | F71: =('FS & Trend Analysis'!E69-'FS & Trend Analysis'!F69)/'FS & Trend Analysis'!F69 -> 1 | G71: =('FS & Trend Analysis'!F69-'FS & Trend Analysis'!G69)/'FS & Trend Analysis'!G69 -> -0.047619048
B72: Investment property | C72: =('FS & Trend Analysis'!B70-'FS & Trend Analysis'!C70)/'FS & Trend Analysis'!C70 -> -0.22666667 | D72: =('FS & Trend Analysis'!C70-'FS & Trend Analysis'!D70)/'FS & Trend Analysis'!D70 -> -0.46043165 | E72: =('FS & Trend Analysis'!D70-'FS & Trend Analysis'!E70)/'FS & Trend Analysis'!E70 -> 4.4940711 | F72: =('FS & Trend Analysis'!E70-'FS & Trend Analysis'!F70)/'FS & Trend Analysis'!F70 -> #DIV/0! | G72: =('FS & Trend Analysis'!F70-'FS & Trend Analysis'!G70)/'FS & Trend Analysis'!G70 -> #DIV/0!
B73: Financial assets
B74: Investments in subsidiaries and associate/joint ventures | C74: =('FS & Trend Analysis'!B72-'FS & Trend Analysis'!C72)/'FS & Trend Analysis'!C72 -> 0.28632479 | D74: =('FS & Trend Analysis'!C72-'FS & Trend Analysis'!D72)/'FS & Trend Analysis'!D72 -> 0.044642857 | E74: =('FS & Trend Analysis'!D72-'FS & Trend Analysis'!E72)/'FS & Trend Analysis'!E72 -> 0.087906751 | F74: =('FS & Trend Analysis'!E72-'FS & Trend Analysis'!F72)/'FS & Trend Analysis'!F72 -> -0.050714615 | G74: =('FS & Trend Analysis'!F72-'FS & Trend Analysis'!G72)/'FS & Trend Analysis'!G72 -> 0.073231074
B75: Trade receivables | C75: =('FS & Trend Analysis'!B73-'FS & Trend Analysis'!C73)/'FS & Trend Analysis'!C73 -> 0.032352941 | D75: =('FS & Trend Analysis'!C73-'FS & Trend Analysis'!D73)/'FS & Trend Analysis'!D73 -> -0.068493151 | E75: =('FS & Trend Analysis'!D73-'FS & Trend Analysis'!E73)/'FS & Trend Analysis'!E73 -> #DIV/0! | F75: =('FS & Trend Analysis'!E73-'FS & Trend Analysis'!F73)/'FS & Trend Analysis'!F73 -> #DIV/0! | G75: =('FS & Trend Analysis'!F73-'FS & Trend Analysis'!G73)/'FS & Trend Analysis'!G73 -> #DIV/0!
B76: Loans | G76: =('FS & Trend Analysis'!F74-'FS & Trend Analysis'!G74)/'FS & Trend Analysis'!G74 -> -1
B77: Other financial assets | C77: =('FS & Trend Analysis'!B75-'FS & Trend Analysis'!C75)/'FS & Trend Analysis'!C75 -> -0.19791667 | D77: =('FS & Trend Analysis'!C75-'FS & Trend Analysis'!D75)/'FS & Trend Analysis'!D75 -> 2.4285714 | E77: =('FS & Trend Analysis'!D75-'FS & Trend Analysis'!E75)/'FS & Trend Analysis'!E75 -> -0.23392613 | F77: =('FS & Trend Analysis'!E75-'FS & Trend Analysis'!F75)/'FS & Trend Analysis'!F75 -> -0.012829169 | G77: =('FS & Trend Analysis'!F75-'FS & Trend Analysis'!G75)/'FS & Trend Analysis'!G75 -> 0.86994949
B78: Deferred tax assets (net) | C78: =('FS & Trend Analysis'!B76-'FS & Trend Analysis'!C76)/'FS & Trend Analysis'!C76 -> 0.83225806 | D78: =('FS & Trend Analysis'!C76-'FS & Trend Analysis'!D76)/'FS & Trend Analysis'!D76 -> -0.12429379 | E78: =('FS & Trend Analysis'!D76-'FS & Trend Analysis'!E76)/'FS & Trend Analysis'!E76 -> 0.1252384 | F78: =('FS & Trend Analysis'!E76-'FS & Trend Analysis'!F76)/'FS & Trend Analysis'!F76 -> 0.10154062 | G78: =('FS & Trend Analysis'!F76-'FS & Trend Analysis'!G76)/'FS & Trend Analysis'!G76 -> -0.16540035
B79: Current tax assets (net) (Non-current) | C79: =('FS & Trend Analysis'!B77-'FS & Trend Analysis'!C77)/'FS & Trend Analysis'!C77 -> 0.087671233 | D79: =('FS & Trend Analysis'!C77-'FS & Trend Analysis'!D77)/'FS & Trend Analysis'!D77 -> -0.18768546 | E79: =('FS & Trend Analysis'!D77-'FS & Trend Analysis'!E77)/'FS & Trend Analysis'!E77 -> 0.027909105 | F79: =('FS & Trend Analysis'!E77-'FS & Trend Analysis'!F77)/'FS & Trend Analysis'!F77 -> 0.08496732 | G79: =('FS & Trend Analysis'!F77-'FS & Trend Analysis'!G77)/'FS & Trend Analysis'!G77 -> 0.16591106
B80: Other non-current assets | C80: =('FS & Trend Analysis'!B78-'FS & Trend Analysis'!C78)/'FS & Trend Analysis'!C78 -> 0.2744186 | D80: =('FS & Trend Analysis'!C78-'FS & Trend Analysis'!D78)/'FS & Trend Analysis'!D78 -> -0.0046296296 | E80: =('FS & Trend Analysis'!D78-'FS & Trend Analysis'!E78)/'FS & Trend Analysis'!E78 -> -0.096989967 | F80: =('FS & Trend Analysis'!E78-'FS & Trend Analysis'!F78)/'FS & Trend Analysis'!F78 -> 0.021349274 | G80: =('FS & Trend Analysis'!F78-'FS & Trend Analysis'!G78)/'FS & Trend Analysis'!G78 -> -0.19629375
B81: Total Non-Current Assets | C81: =('FS & Trend Analysis'!B79-'FS & Trend Analysis'!C79)/'FS & Trend Analysis'!C79 -> 0.04075878 | D81: =('FS & Trend Analysis'!C79-'FS & Trend Analysis'!D79)/'FS & Trend Analysis'!D79 -> 0.047529538 | E81: =('FS & Trend Analysis'!D79-'FS & Trend Analysis'!E79)/'FS & Trend Analysis'!E79 -> 0.11157543 | F81: =('FS & Trend Analysis'!E79-'FS & Trend Analysis'!F79)/'FS & Trend Analysis'!F79 -> -0.05174073 | G81: =('FS & Trend Analysis'!F79-'FS & Trend Analysis'!G79)/'FS & Trend Analysis'!G79 -> 0.057151406
B83: Current Assets
B84: Inventories | C84: =('FS & Trend Analysis'!B82-'FS & Trend Analysis'!C82)/'FS & Trend Analysis'!C82 -> 0.15357918 | D84: =('FS & Trend Analysis'!C82-'FS & Trend Analysis'!D82)/'FS & Trend Analysis'!D82 -> 0.1173049 | E84: =('FS & Trend Analysis'!D82-'FS & Trend Analysis'!E82)/'FS & Trend Analysis'!E82 -> -0.074887892 | F84: =('FS & Trend Analysis'!E82-'FS & Trend Analysis'!F82)/'FS & Trend Analysis'!F82 -> 0.030356235 | G84: =('FS & Trend Analysis'!F82-'FS & Trend Analysis'!G82)/'FS & Trend Analysis'!G82 -> 0.092529026
B85: Financial assets
B86: Investments | C86: =('FS & Trend Analysis'!B84-'FS & Trend Analysis'!C84)/'FS & Trend Analysis'!C84 -> 0.3207331 | D86: =('FS & Trend Analysis'!C84-'FS & Trend Analysis'!D84)/'FS & Trend Analysis'!D84 -> 0.45742905 | E86: =('FS & Trend Analysis'!D84-'FS & Trend Analysis'!E84)/'FS & Trend Analysis'!E84 -> 1.3416732 | F86: =('FS & Trend Analysis'!E84-'FS & Trend Analysis'!F84)/'FS & Trend Analysis'!F84 -> 0.15173345 | G86: =('FS & Trend Analysis'!F84-'FS & Trend Analysis'!G84)/'FS & Trend Analysis'!G84 -> #DIV/0!
B87: Trade receivables | C87: =('FS & Trend Analysis'!B85-'FS & Trend Analysis'!C85)/'FS & Trend Analysis'!C85 -> 0.092457421 | D87: =('FS & Trend Analysis'!C85-'FS & Trend Analysis'!D85)/'FS & Trend Analysis'!D85 -> 0.19001086 | E87: =('FS & Trend Analysis'!D85-'FS & Trend Analysis'!E85)/'FS & Trend Analysis'!E85 -> 0.15956018 | F87: =('FS & Trend Analysis'!E85-'FS & Trend Analysis'!F85)/'FS & Trend Analysis'!F85 -> 0.03505495 | G87: =('FS & Trend Analysis'!F85-'FS & Trend Analysis'!G85)/'FS & Trend Analysis'!G85 -> 0.065737697
B88: Cash and cash equivalents | C88: =('FS & Trend Analysis'!B86-'FS & Trend Analysis'!C86)/'FS & Trend Analysis'!C86 -> -0.25652174 | D88: =('FS & Trend Analysis'!C86-'FS & Trend Analysis'!D86)/'FS & Trend Analysis'!D86 -> 0.12634672 | E88: =('FS & Trend Analysis'!D86-'FS & Trend Analysis'!E86)/'FS & Trend Analysis'!E86 -> 11.542998 | F88: =('FS & Trend Analysis'!E86-'FS & Trend Analysis'!F86)/'FS & Trend Analysis'!F86 -> 2.0148148 | G88: =('FS & Trend Analysis'!F86-'FS & Trend Analysis'!G86)/'FS & Trend Analysis'!G86 -> -0.45121951
B89: Bank balances other than cash and cash equivalents | C89: =('FS & Trend Analysis'!B87-'FS & Trend Analysis'!C87)/'FS & Trend Analysis'!C87 -> 0.64847512 | D89: =('FS & Trend Analysis'!C87-'FS & Trend Analysis'!D87)/'FS & Trend Analysis'!D87 -> 2.3138298 | E89: =('FS & Trend Analysis'!D87-'FS & Trend Analysis'!E87)/'FS & Trend Analysis'!E87 -> 1.4479167 | F89: =('FS & Trend Analysis'!E87-'FS & Trend Analysis'!F87)/'FS & Trend Analysis'!F87 -> 12.241379 | G89: =('FS & Trend Analysis'!F87-'FS & Trend Analysis'!G87)/'FS & Trend Analysis'!G87 -> -0.049180328
B90: Loans | C90: =('FS & Trend Analysis'!B88-'FS & Trend Analysis'!C88)/'FS & Trend Analysis'!C88 -> -0.95454545 | D90: =('FS & Trend Analysis'!C88-'FS & Trend Analysis'!D88)/'FS & Trend Analysis'!D88 -> 1.2 | E90: =('FS & Trend Analysis'!D88-'FS & Trend Analysis'!E88)/'FS & Trend Analysis'!E88 -> -0.90800368 | F90: =('FS & Trend Analysis'!E88-'FS & Trend Analysis'!F88)/'FS & Trend Analysis'!F88 -> -0.21685879 | G90: =('FS & Trend Analysis'!F88-'FS & Trend Analysis'!G88)/'FS & Trend Analysis'!G88 -> 0.38109453
B91: Other financial assets | C91: =('FS & Trend Analysis'!B89-'FS & Trend Analysis'!C89)/'FS & Trend Analysis'!C89 -> -0.77220077 | D91: =('FS & Trend Analysis'!C89-'FS & Trend Analysis'!D89)/'FS & Trend Analysis'!D89 -> 5.475 | E91: =('FS & Trend Analysis'!D89-'FS & Trend Analysis'!E89)/'FS & Trend Analysis'!E89 -> -0.70695971 | F91: =('FS & Trend Analysis'!E89-'FS & Trend Analysis'!F89)/'FS & Trend Analysis'!F89 -> 0.69354839 | G91: =('FS & Trend Analysis'!F89-'FS & Trend Analysis'!G89)/'FS & Trend Analysis'!G89 -> -0.60625305
B92: Other current assets | C92: =('FS & Trend Analysis'!B90-'FS & Trend Analysis'!C90)/'FS & Trend Analysis'!C90 -> 0.31649832 | D92: =('FS & Trend Analysis'!C90-'FS & Trend Analysis'!D90)/'FS & Trend Analysis'!D90 -> -0.11077844 | E92: =('FS & Trend Analysis'!D90-'FS & Trend Analysis'!E90)/'FS & Trend Analysis'!E90 -> 0.29557797 | F92: =('FS & Trend Analysis'!E90-'FS & Trend Analysis'!F90)/'FS & Trend Analysis'!F90 -> 0.035341365 | G92: =('FS & Trend Analysis'!F90-'FS & Trend Analysis'!G90)/'FS & Trend Analysis'!G90 -> -0.16330645
B93: Assets classified as held for sale
B94: Total Current Assets | C94: =('FS & Trend Analysis'!B92-'FS & Trend Analysis'!C92)/'FS & Trend Analysis'!C92 -> 0.11194284 | D94: =('FS & Trend Analysis'!C92-'FS & Trend Analysis'!D92)/'FS & Trend Analysis'!D92 -> 0.25634084 | E94: =('FS & Trend Analysis'!D92-'FS & Trend Analysis'!E92)/'FS & Trend Analysis'!E92 -> 0.26912366 | F94: =('FS & Trend Analysis'!E92-'FS & Trend Analysis'!F92)/'FS & Trend Analysis'!F92 -> 0.065533653 | G94: =('FS & Trend Analysis'!F92-'FS & Trend Analysis'!G92)/'FS & Trend Analysis'!G92 -> 0.081367728
B95: TOTAL ASSETS | C95: =('FS & Trend Analysis'!B93-'FS & Trend Analysis'!C93)/'FS & Trend Analysis'!C93 -> 0.090108508 | D95: =('FS & Trend Analysis'!C93-'FS & Trend Analysis'!D93)/'FS & Trend Analysis'!D93 -> 0.18395085 | E95: =('FS & Trend Analysis'!D93-'FS & Trend Analysis'!E93)/'FS & Trend Analysis'!E93 -> 0.20968468 | F95: =('FS & Trend Analysis'!E93-'FS & Trend Analysis'!F93)/'FS & Trend Analysis'!F93 -> 0.018033407 | G95: =('FS & Trend Analysis'!F93-'FS & Trend Analysis'!G93)/'FS & Trend Analysis'!G93 -> 0.071426817

Sheet Cash Flow Statement
A1: Cash Flow Statement
A3: Particulars
A4: Cash Flow from Operating Activities | B4: March 31, 2026 | C4: March 31, 2025 | D4: March 31, 2024 | E4: March 31, 2023 | F4: March 31, 2022
A5: Depreciation and amortisation expense | B5: 283 | C5: 274 | D5: 264 | E5: 270.6 | F5: 288.6
A6: Employee share-based payment expense | B6: 22 | C6: 17 | D6: 37 | E6: 23.3 | F6: 25.2
A7: Loss allowance on trade receivables, other assets and other financial assets (net) | B7: 35 | C7: -9 | D7: 41 | E7: -12 | F7: -12.9
A8: Provision on doubtful other assets | B8: 0 | C8: 0 | D8: 0 | E8: 17.3 | F8: 15.8
A9: Profit on redemption/sale of investments | B9: -77 | C9: -25 | D9: -42 | E9: -16.6 | F9: 0
A10: Increase in fair value of investments | B10: -31 | C10: -16 | D10: -18 | E10: -2.5 | F10: 0
A11: Finance costs | B11: 158 | C11: 89 | D11: 76 | E11: 103.9 | F11: 88
A12: Dividend income from a subsidiary | B12: -101 | C12: -120 | D12: -125 | E12: 0 | F12: 0
A13: Gain on disposal of property, plant and equipment (net) | B13: -22 | C13: -99 | D13: -13 | E13: -20.3 | F13: -12.3
A14: Interest income | B14: -76 | C14: -73 | D14: -39 | E14: -34.2 | F14: -19.4
A15: Interest on direct and indirect tax refund | B15: -1 | C15: -1 | D15: -87 | E15: 0 | F15: 0
A16: Interest income from loan to subsidiary and joint venture | B16: -1 | C16: -1 | D16: 0 | E16: 0 | F16: 0
... A29: Income taxes paid (net of refunds) | B29: -334 | C29: -173 | D29: -313 | E29: -296.5 | F29: -457.6
A30: Net cash from operating activities | B30: =B28+B29 -> 1483 | C30: =C28+C29 -> 1606 | D30: =D28+D29 -> 912 | E30: =E28+E29 -> 576.6 | F30: =F28+F29 -> 911.3
A32: Cash Flow from Investing Activities
A33: Purchase of property, plant and equipment and intangible assets | B33: -181 | C33: -162 | D33: -98 | E33: -139.7 | F33: -134.6
A34: Proceeds from sale of property, plant and equipment and investment property | B34: 253 | C34: 1 | D34: 20 | E34: 26.5 | F34: 38.3
A35: Purchase of current investments | B35: -1862 | C35: -1246 | D35: -760 | E35: -8529.5 | F35: -1435.6
A36: Redemption of current investments | B36: 1688 | C36: 1011 | D36: 478 | E36: 8752.3 | F36: 1213.5
A37: Investment in term deposits with banks | B37: -1113 | C37: -1083 | D37: -400 | E37: -101.3 | F37: 0
A38: Redemption of term deposits from banks | B38: 790 | C38: 395 | D38: 980 | E38: 25 | F38: 0
A39: Investment in an associate/subsidiary/joint ventures | B39: -97 | C39: -13 | D39: -15 | E39: -31.5 | F39: 0
A40: Loans given to subsidiaries and joint ventures | B40: 0 | C40: -18 | D40: -29 | E40: -326.3 | F40: -249.9
A41: Repayment of loans by subsidiary and joint venture | B41: 18 | C41: 0 | D41: 121 | E41: 361.3 | F41: 321
A42: Repayment of loans given to others | B42: 3 | C42: 7 | D42: 6 | E42: 3.2 | F42: 0
A43: Loans given to others | B43: 0 | C43: 0 | D43: 0 | E43: -8 | F43: -10
A44: Interest received | B44: 65 | C44: 38 | D44: 39 | E44: 20.4 | F44: 17
... A49: Proceeds from disposal of investment in an associate | B49: 0 | C49: 0 | D49: 0 | E49: 0 | F49: 0.5
A50: Net cash from operating activities | B50: =SUM(B33:B49) -> -335 | C50: =SUM(C33:C49) -> -950 | D50: =SUM(D33:D49) -> 467 | E50: =SUM(E33:E49) -> 902.4 | F50: =SUM(F33:F49) -> -230.9
A55: Cash Flow from Financing Activities
A56: Net proceeds / (repayment) of working capital loans | B56: 0 | C56: 0 | D56: 0 | E56: -339.2 | F56: -535.7
A57: Repayment of deferred sales tax liability | B57: 0 | C57: -1 | D57: -1 | E57: -1.4 | F57: -2
A58: Interest paid on borrowings | B58: 0 | C58: 0 | D58: 0 | E58: -20.3 | F58: -38
A59: Dividend paid | B59: -1263 | C59: -350 | D59: -291 | E59: 0 | F59: 0
A60: Principal repayment of lease liabilities | B60: -143 | C60: -137 | D60: -126 | E60: -124 | F60: -100.2
A61: Interest paid on lease liabilities | B61: -37 | C61: -40 | D61: -21 | E61: -16 | F61: -11.9
A62: Net cash (used) in financing activities | B62: =SUM(B56:B61) -> -1443 | C62: =SUM(C56:C61) -> -528 | D62: =SUM(D56:D61) -> -439 | E62: =SUM(E56:E61) -> -500.9 | F62: =SUM(F56:F61) -> -687.8
A64: Net increase / (decrease) in cash and cash equivalents [D = A+B+C] | B64: -295 | C64: 129 | D64: 940 | E64: 54.4 | F64: -22.2
A65: Cash and cash equivalents as at the beginning of the year (E) | B65: 1150 | C65: 1021 | D65: 81 | E65: 27 | F65: 49.2
A66: Cash and cash equivalents taken over on account of amalgamation | B66: 0 | C66: 0 | D66: 0 | E66: 0 | F66: 0
A67: Effects of exchange rate changes on cash and cash equivalents | B67: 0 | C67: 0 | D67: 0 | E67: 0 | F67: 0
A68: Net increase / (decrease) in cash and cash equivalents | B68: -295 | C68: 129 | D68: 940 | E68: 54.4 | F68: -22.2
A69: Cash and cash equivalents as at the end of the year [D+E] | B69: 855 | C69: 1150 | D69: 1021 | E69: 81.4 | F69: 27
A70: Non-cash financing and investing activities
A71: Acquisition of right-of-use assets | B71: 71 | C71: 394 | D71: 184 | E71: 86 | F71: 229.2

Sheet Shareholding
A2: Promoter Group | B2: 0.346
A3: Foreign Institutional Investors (FII) | B3: 0.343
A4: Non Resident Indians (NRIs) | B4: 0.004
A5: Indian Public | B5: 0.083
A6: Insurance companies | B6: 0.083
A7: Mutual Funds / UTI | B7: 0.082
A8: Bodies Corporate | B8: 0.014
A9: Financial Institutions / Banks | B9: 0.02
A10: Others | B10: 0.025

Sheet Line Item Meanings
A1: INCOME STATEMENT — Line Item Meanings
A3: Income
A4: Revenue from Operations | B4: The money the company earns from its core business — in Diageo India's case, this is the sale of alcoholic beverages (spirits, beer, wine). It includes excise duty collected from customers. This is the top line of the P&L.
A5: Other Income | B5: Earnings that do not come from the main business. Examples: interest earned on bank deposits, profit on sale of investments, dividend received from subsidiaries, rental income, or gains on foreign exchange.
A6: Total Income | B6: Revenue from Operations + Other Income. Represents the total money flowing into the company during the year from all sources.
A8: Expenses
A9: Cost of Materials Consumed (Raw Material) | B9: The cost of raw materials (grain, molasses, glass bottles, packaging, etc.) used up during the year to manufacture the products. Formula: Opening stock of raw materials + Purchases − Closing stock.
A10: Purchase of Stock-in-Trade | B10: Cost of buying finished goods from outside for resale without any further manufacturing — for example, imported scotch or wine bought and sold as-is.
A11: Change in Inventories of FG, WIP & Stock-in-Trade | B11: Adjusts expenses to reflect actual production cost. If closing inventory > opening inventory (production exceeded sales), it is negative (reduces total expense). If the opposite, it is positive (adds to expense).
A12: Excise Duty | B12: Government tax levied on the manufacture/sale of alcoholic beverages. This is the single largest expense for liquor companies in India and is passed on to consumers as part of MRP.
A13: Employee Benefits Expense | B13: All costs related to employees — salaries & wages, bonus, PF/gratuity contributions, ESOP costs, staff welfare, and retirement benefit provisions.
A14: Advertisement and Sales Promotion | B14: Money spent on brand building, advertising (surrogate ads for liquor in India), sponsorships, trade promotions, point-of-sale materials, and consumer sampling.
A15: Other Expenses | B15: All remaining operating expenses — rent, repairs & maintenance, power & fuel, legal fees, audit fees, travel, insurance, IT costs, commission to distributors, freight & transport, etc.
A16: Total Expenses | B16: Sum of all the expense items above. Represents the total cost the company incurred to run its operations during the year.
A18: Profitability Measures
A19: EBITDA (Earnings Before Interest, Tax, Depreciation & Amortisation) | B19: Total Income minus Total Expenses (before deducting depreciation, interest, and tax). Shows the profit generated purely from operations — the best measure of operating cash-generating ability.
A20: Depreciation and Amortisation Expense | B20: Non-cash charge that spreads the cost of fixed assets (plant, machinery, buildings) and intangible assets (software, licenses) over their useful life. Reflects wear-and-tear and obsolescence.
A21: EBIT (Earnings Before Interest and Tax) | B21: EBITDA minus Depreciation. Shows operating profit after accounting for asset usage but before financing costs and taxes. Also called Operating Profit.
A22: Finance Costs | B22: Interest and other charges paid on borrowed money — includes interest on bank loans, lease liabilities, commercial paper, and any other debt instruments.
A23: PBT before Profits of JVs | B23: Profit Before Tax calculated before adding the company's share of profit/loss from joint ventures. Equals EBIT minus Finance Costs.
A24: Add: Share of Profits of JVs | B24: The company's proportionate share of net profit or loss from joint ventures accounted under the equity method. Zero means no active JV contributing profit.
A25: PBT & Exceptional Items | B25: Profit Before Tax before adjusting for one-time exceptional items. This is the recurring operating profitability number.
A26: Exceptional Items | B26: One-off, non-recurring gains or losses — such as profit/loss on sale of a factory, impairment of goodwill, restructuring charges, or legal settlement costs. Shown separately so analysts can see the 'clean' recurring profit.
A27: PBT (Profit Before Tax) | B27: The profit after all expenses including exceptional items but before paying income tax. PBT = PBT & Exceptional Items + Exceptional Items.
A28: Tax | B28: Income tax expense for the year — includes current tax (payable now) and deferred tax (timing differences between book profit and taxable profit).
A29: PAT (Profit After Tax) | B29: The bottom line — net profit remaining after all expenses and taxes. This is what belongs to the shareholders of the company.
A30: Less: Share of Minority Interest | B30: Portion of PAT that belongs to outside (minority) shareholders of subsidiaries — not to the parent company's shareholders. Zero means the company owns 100% of all subsidiaries.
... A33: Tax Rate (%) | B33: Effective tax rate = Tax / PBT. Shows what percentage of pre-tax profit goes to the government. Varies due to deferred tax adjustments, tax incentives, and prior-period items.
A36: BALANCE SHEET — Line Item Meanings
A38: Equity & Liabilities
A39: Share Capital | B39: The face value of all equity shares issued by the company. For Diageo India, each share has a face value of ₹10. This rarely changes unless new shares are issued or bought back.
A40: Share Suspense | B40: Shares allotted but pending final settlement formalities (e.g., ESOP shares awaiting exercise completion). Typically a very small or zero amount.
A41: Reserves and Surplus (Other Equity) | B41: Accumulated retained earnings over the years (profits not paid out as dividends), plus share premium, general reserve, and other reserves. This is the shareholders' wealth built up inside the company.
A42: Total Equity | B42: Share Capital + Share Suspense + Reserves & Surplus. Represents the net worth — the shareholders' total claim on the company's assets after all liabilities are paid.
A44: Non-Current Liabilities (due after more than 1 year)
A45: Borrowings (Non-Current) | B45: Long-term loans from banks or financial institutions that are due for repayment after more than one year. Zero means the company has no long-term debt — a sign of strong financial health.
A46: Lease Liabilities (Non-Current) | B46: The long-term portion of obligations under lease agreements (warehouses, offices, vehicles). Under Ind AS 116, operating leases are now recorded on the balance sheet.
A47: Provisions (Non-Current) | B47: Amounts set aside for known future obligations that will be settled beyond one year — such as employee gratuity, long-term leave encashment, or asset retirement obligations.
A48: Total Non-Current Liabilities | B48: Sum of all long-term obligations. A lower figure relative to equity means the company relies less on long-term debt to fund its operations.
A50: Current Liabilities (due within 1 year)
A51: Borrowings (Current / Short-Term) | B51: Short-term loans, working capital facilities, or commercial paper that must be repaid within one year. Includes cash credit and overdraft facilities from banks.
A52: Lease Liabilities (Current) | B52: The portion of lease payments due within the next 12 months — the current year's rent obligation for leased assets.
A53: Trade Payables — MSME | B53: Amounts owed to micro and small enterprise suppliers for raw materials, goods, or services purchased on credit. Separately disclosed as required by MSMED Act.
A54: Trade Payables — Other Creditors | B54: Amounts owed to all other suppliers (large companies, importers, service providers) for goods and services bought on credit.
A55: Other Financial Liabilities | B55: Short-term financial obligations other than borrowings and trade payables — such as interest accrued but not yet paid, security deposits from distributors, or unpaid capital expenditure bills.
A56: Provisions (Current) | B56: Amounts set aside for obligations expected to be settled within one year — such as excise duty disputes, sales tax demands under litigation, warranty claims, or employee bonus payable.
A57: Current Tax Liabilities (Net) | B57: Income tax payable to the government for the current year, net of advance tax already paid. A positive balance means tax still owed.
A58: Other Current Liabilities | B58: Miscellaneous short-term obligations — statutory dues payable (GST, TDS), advances received from customers, deferred revenue, and any other amounts due within one year.
A59: Total Current Liabilities | B59: Sum of all obligations due within one year. Compared against Current Assets to assess the company's short-term liquidity position.
A60: TOTAL EQUITIES & LIABILITIES | B60: Total Equity + Total Non-Current Liabilities + Total Current Liabilities. Must always equal Total Assets (the fundamental accounting equation).
A62: Non-Current Assets (held for more than 1 year)
A63: Property, Plant and Equipment (PPE) | B63: Physical assets used in operations — land, buildings, manufacturing plant, machinery, furniture, vehicles, and office equipment. Shown at cost minus accumulated depreciation.
A64: Right-of-Use Assets | B64: The value of assets used under lease agreements (warehouses, offices, vehicles) recognized under Ind AS 116. Depreciated over the lease term.
A65: Capital Work-in-Progress (CWIP) | B65: Cost of assets (plant, buildings, equipment) that are under construction or installation and not yet ready for use. Once completed, they move to PPE.
A66: Intangible Assets | B66: Non-physical assets with economic value — such as computer software, licenses, trademarks, and brand rights. Amortised over their useful life.
A67: Intangible Assets Under Development | B67: Intangible assets being developed but not yet complete — for example, software under development or pending patent applications.
A68: Investment Property | B68: Property (land or buildings) held to earn rental income or for capital appreciation, not used in the company's own operations. Shown separately from PPE.
A69: Investments in Subsidiaries and Associates/JVs | B69: Money invested in subsidiary companies, associates, or joint ventures. Shown at cost or equity method. Represents the company's ownership stake in other entities.
A70: Trade Receivables (Non-Current) | B70: Amounts owed by customers for goods sold on credit that are expected to be collected beyond one year. Unusual for FMCG; may indicate long-term settlement arrangements.
A71: Loans (Non-Current) | B71: Long-term loans given to subsidiaries, employees, or others that are due for repayment after more than one year.
A72: Other Financial Assets (Non-Current) | B72: Long-term financial assets such as security deposits paid, fixed deposits with banks maturing beyond one year, or derivative instruments.
A73: Deferred Tax Assets (Net) | B73: Tax benefit arising from timing differences — e.g., when the company has paid more tax now than required under accounting rules, and will pay less in the future. Net of deferred tax liabilities.
A74: Current Tax Assets (Net) — Non-Current | B74: Advance income tax and TDS paid in excess of the actual tax liability for previous years. Shown as non-current because tax refund disputes with the government can take years to resolve.
... A76: Total Non-Current Assets | B76: Sum of all assets held for more than one year. Represents the long-term infrastructure and investments that support the company's operations.
A78: Current Assets (convertible to cash within 1 year)
A79: Inventories | B79: Stock of goods at various stages — raw materials (grain, bottles), work-in-progress (maturing spirits), finished goods (ready-to-sell bottles), and stock-in-trade (purchased goods for resale).
A80: Investments (Current) | B80: Short-term investments in mutual funds, treasury bills, or fixed deposits maturing within one year. Parked to earn returns on surplus cash.
A81: Trade Receivables (Current) | B81: Amounts owed by customers (distributors, retailers) for goods sold on credit, expected to be collected within the normal credit period (typically 30–90 days).
A82: Cash and Cash Equivalents | B82: Money readily available — cash on hand, balances in current accounts with banks, and highly liquid investments maturing within 3 months (e.g., short-term FDs).
A83: Bank Balances Other Than Cash and Cash Equivalents | B83: Fixed deposits or earmarked bank balances that do not qualify as cash equivalents — such as deposits with maturity beyond 3 months, or balances held as margin money.
A84: Loans (Current) | B84: Short-term loans given to subsidiaries, employees, or others that are due for repayment within one year.
A85: Other Financial Assets (Current) | B85: Short-term financial assets — such as interest accrued on deposits, insurance claims receivable, derivative instruments, or deposits with government authorities.
A86: Other Current Assets | B86: Miscellaneous short-term assets — advance payments to suppliers, prepaid insurance, GST/excise duty refunds receivable, and balances with statutory authorities.
A87: Assets Classified as Held for Sale | B87: Assets the company has decided to sell rather than continue using — such as a closed factory or surplus land. Shown at the lower of carrying value or expected sale price.
A88: Total Current Assets | B88: Sum of all assets expected to be converted into cash within one year. Compared against Current Liabilities to assess short-term solvency.
A89: TOTAL ASSETS | B89: Total Non-Current Assets + Total Current Assets. Must always equal Total Equities & Liabilities. Represents everything the company owns.
A92: CASH FLOW STATEMENT — Line Item Meanings
A94: A. Cash Flow from Operating Activities
A95: Starting Point: PBT | B95: The cash flow statement starts with Profit Before Tax from the income statement, and then adjusts for all non-cash items and working capital changes to arrive at actual cash generated.
A96: Depreciation and Amortisation (add back) | B96: Added back because it is a non-cash expense — no actual cash left the company. The cash was spent when the asset was originally purchased.
A97: Employee Share-Based Payment Expense (add back) | B97: Non-cash expense representing the fair value of stock options (ESOPs) granted to employees. Added back because no cash was paid — the cost is the dilution of equity.
A98: Loss Allowance on Trade Receivables (add back / deduct) | B98: Provision for expected bad debts. If positive (provision created), added back as non-cash. If negative (reversal of earlier provision), deducted.
A99: Finance Costs (add back) | B99: Added back here because it will be shown separately under financing activities. This avoids double-counting — operating profit should exclude financing decisions.
A100: Gain on Disposal of PPE (deduct) | B100: Profit on selling fixed assets is deducted because it is a non-operating item — the actual cash inflow from the sale appears under Investing Activities.
A101: Interest Income (deduct) | B101: Removed from operating profit because it is not from core operations. The actual cash received appears under Investing Activities.
A102: Exceptional Items (add back / deduct) | B102: Non-recurring items are reversed out so operating cash flow reflects only regular business activity. The cash effect appears elsewhere if applicable.
A103: Operating Profit Before Working Capital Changes | B103: PBT adjusted for all non-cash and non-operating items. This is the cash the business would generate if there were no changes in working capital.
A105: Working Capital Adjustments
A106: (Increase) / Decrease in Trade Receivables | B106: If receivables increased, the company sold goods but hasn't collected cash yet — cash outflow. If decreased, collections exceeded new sales — cash inflow.
A107: (Increase) / Decrease in Inventories | B107: If inventory increased, the company spent cash to build stock — cash outflow. If decreased, the company sold from existing stock — cash inflow.
A108: Increase / (Decrease) in Trade Payables | B108: If payables increased, the company bought materials on credit without paying yet — cash inflow (conservation). If decreased, the company paid off suppliers — cash outflow.
A109: (Increase) / Decrease in Loans & Other Financial Assets | B109: Changes in short-term loans given or financial assets held. An increase means cash was deployed; a decrease means cash was recovered.
A110: (Increase) / Decrease in Other Assets | B110: Changes in prepaid expenses, advances, and other miscellaneous assets. An increase means cash was spent upfront; a decrease means prior advances were adjusted.
A111: Increase / (Decrease) in Other Liabilities | B111: Changes in statutory dues, customer advances, and other obligations. An increase means cash was received or retained; a decrease means obligations were settled.
A112: Increase / (Decrease) in Provisions | B112: Changes in provisions for excise disputes, employee benefits, etc. An increase adds to operating cash (obligation recognized but not paid); a decrease means provisions were used (cash paid out).
A113: Cash Generated from Operations | B113: Operating profit after adjusting for working capital changes. This is the actual cash produced by day-to-day business before paying taxes.
A114: Income Taxes Paid (Net of Refunds) | B114: Actual cash paid to the tax authorities during the year, net of any refunds received. Different from tax expense in P&L due to advance tax and prior-year adjustments.
A115: Net Cash from Operating Activities | B115: The final operating cash flow — the actual cash the core business generated after paying taxes. This is the most important number for assessing business health.
A117: B. Cash Flow from Investing Activities
A118: Purchase of PPE and Intangible Assets (Capex) | B118: Cash spent on buying new factories, machinery, equipment, software, or other long-term assets. This is capital expenditure — investment in future capacity.
...
